Workbook
Name Slicer_Date_Hierarchy: #N/A
Name Slicer_Region: #N/A
Name Slicer_Status: #N/A

Sheet Dashboard
AU23: #5E82A6
AX47: #96ADC4

Sheet Analysis
A1: Total Revenue By Region
A2: East | B2: =SUMIFS(Table1[Net Revenue],Table1[Region],"East",Table1[Status],"Completed") -> 153956200 | E2: Insights | I2: KPIs
A3: West | B3: =SUMIFS(Table1[Net Revenue],Table1[Region],"West",Table1[Status],"Completed") -> 63334700 | E3: Revenue By Region | I3: Revenue | K3: Orders
A4: North | B4: =SUMIFS(Table1[Net Revenue],Table1[Region],"North",Table1[Status],"Completed") -> 146717750 | E4: Row Labels | F4: Total Revenue | I4: Total Revenue | K4: Total Orders | M4: AOV | O4: Return Rate | Q4: Qty Sold | S4: Total Discount
A5: South | B5: =SUMIFS(Table1[Net Revenue],Table1[Region],"South",Table1[Status],"Completed") -> 98893650 | E5: East | F5: 153956200 | I5: 462902300 | K5: 424 | M5: 1718994.2 | O5: 0.23474178 | Q5: 2867 | S5: 35825700
E6: North | F6: 146717750
A7: Count Of Completed Orders By Sales Rep | E7: South | F7: 98893650
A8: Yemi Osinbajo | B8: =COUNTIFS(Table1[Status],"Completed",Table1[Sales Rep],"Yemi Osinbajo") -> 30 | E8: West | F8: 63334700
A9: Fatima Aliyu | B9: =COUNTIFS(Table1[Status],"Completed",Table1[Sales Rep],"Fatima Aliyu") -> 32 | E9: Grand Total | F9: 462902300 | I9: =I5 -> 462902300 | K9: =K5 -> 424 | M9: =M5 -> 1718994.2 | O9: =O5 -> 0.23474178 | Q9: =Q5 -> 2867 | S9: =S5 -> 35825700
A10: James Okafor | B10: =COUNTIFS(Table1[Status],"Completed",Table1[Sales Rep],"James Okafor") -> 20
A11: Ngozi Adeyemi | B11: =COUNTIFS(Table1[Status],"Completed",Table1[Sales Rep],"Ngozi Adeyemi") -> 29
A12: Emeka Nwosu | B12: =COUNTIFS(Table1[Status],"Completed",Table1[Sales Rep],"Emeka Nwosu") -> 28 | E12: Monthly Revenue Trend
A13: Ibrahim Musa | B13: =COUNTIFS(Table1[Status],"Completed",Table1[Sales Rep],"Ibrahim Musa") -> 22 | E13: Row Labels | F13: Total Revenue
A14: Tunde Fashola | B14: =COUNTIFS(Table1[Status],"Completed",Table1[Sales Rep],"Tunde Fashola") -> 28 | E14: Jan | F14: 49635800
A15: Amaka Bello | B15: =COUNTIFS(Table1[Status],"Completed",Table1[Sales Rep],"Amaka Bello") -> 23 | E15: Feb | F15: 20624150
A16: Kemi Adebayo | B16: =COUNTIFS(Table1[Status],"Completed",Table1[Sales Rep],"Kemi Adebayo") -> 24 | E16: Mar | F16: 53819600
A17: Chukwudi Eze | B17: =COUNTIFS(Table1[Status],"Completed",Table1[Sales Rep],"Chukwudi Eze") -> 22 | E17: Apr | F17: 37960500
E18: May | F18: 19575650
A19: Avg Unit Price For Electronics In the North Region | E19: Jun | F19: 40644250
A20: =AVERAGEIFS(Table1[Unit Price Clean],Table1[Category],"Accessories",Table1[Region],"North") -> 24847.458 | E20: Jul | F20: 34914400
E21: Aug | F21: 46695850
A22: Weighted Average Discount Across all Orders | E22: Sept | F22: 35852750
A23: =AVERAGE(Table1[Discount]) -> 139738.76 | E23: Oct | F23: 54232000
E24: Nov | F24: 28664000
A25: Top 5 Orders | E25: Dec | F25: 40283350
A26: =LARGE(Table1[Net Revenue],5) -> 8550000 | E26: Grand Total | F26: 462902300
A28: Bottom 5 Revenue Orders | E28: Revenue By Channel
A29: =SMALL(Table1[Net Revenue],5) -> 22400 | E29: Row Labels | F29: Total Revenue
E30: Distributor | F30: 99967000
E31: In-Store | F31: 202267050
E32: Online | F32: 156840250
E36: Top 5 Revenue By Sales Rep
E37: Row Labels | F37: Total Revenue
E38: Fatima Aliyu | F38: 43671400
E39: Amaka Bello | F39: 50752150
E40: Ngozi Adeyemi | F40: 52015100
E41: Emeka Nwosu | F41: 60132500
E42: Yemi Osinbajo | F42: 63432700
E44: Status By Orders
E45: Row Labels | F45: Total Orders
E46: Cancelled | F46: 51
E47: Completed | F47: 259
E48: Pending | F48: 65
E49: Returned | F49: 49
E50: Grand Total | F50: 424
E52: Revenue By Category
E53: Row Labels | F53: Total Revenue
E54: Accessories | F54: 27773800
E55: Electronics | F55: 435128500
E56: Grand Total | F56: 462902300
E60: Row Labels | F60: Return Rate
E61: Monitor 4K | F61: 0.38297872
E62: Mouse Ergo | F62: 0.29411765
E63: SmartPhone X | F63: 0.24615385
E64: Laptop Pro | F64: 0.24418605
E65: Tablet Air | F65: 0.19607843
E66: Keyboard Mech | F66: 0.18181818
E67: Webcam HD | F67: 0.15217391
E68: Wireless Earbuds | F68: 0.13888889
E69: Grand Total | F69: 0.23474178

Sheet Pivot Table
A2: Revenue By Sales Rep and Region
A3: Total Revenue | B3: Column Labels
A4: Row Labels | B4: East | C4: North | D4: South | E4: West | F4: Grand Total
A5: Amaka Bello | B5: 14885600 | C5: 13800650 | D5: 13880400 | E5: 8185500 | F5: 50752150
A6: Chukwudi Eze | B6: 14858600 | C6: 3647300 | D6: 4613600 | E6: 546000 | F6: 23665500
A7: Emeka Nwosu | B7: 20403000 | C7: 11418200 | D7: 10578500 | E7: 17732800 | F7: 60132500
A8: Fatima Aliyu | B8: 16973750 | C8: 17167700 | D8: 6720950 | E8: 2809000 | F8: 43671400
A9: Ibrahim Musa | B9: 13409750 | C9: 25344400 | D9: 5352000 | E9: 1403200 | F9: 45509350
A10: James Okafor | B10: 5470600 | C10: 13855750 | D10: 9576000 | E10: 7164000 | F10: 36066350
A11: Kemi Adebayo | B11: 28076000 | C11: 15844500 | D11: 11539400 | E11: 89600 | F11: 55549500
A12: N/A | C12: 324000 | D12: 2907000 | E12: 3060000 | F12: 6291000
A13: Ngozi Adeyemi | B13: 12344500 | C13: 18571100 | D13: 5945900 | E13: 15153600 | F13: 52015100
A14: Tunde Fashola | B14: 3571900 | C14: 14793450 | D14: 920400 | E14: 6531000 | F14: 25816750
A15: Yemi Osinbajo | B15: 23962500 | C15: 11950700 | D15: 26859500 | E15: 660000 | F15: 63432700
A16: Grand Total | B16: 153956200 | C16: 146717750 | D16: 98893650 | E16: 63334700 | F16: 462902300
A18: Product Insights
A19: Row Labels | B19: Count of Order ID | C19: Sum of Unit Price Clean | D19: Qty Sold
A20: Keyboard Mech | B20: 44 | C20: 1232000 | D20: 310
A21: Laptop Pro | B21: 86 | C21: 38700000 | D21: 628
A22: Monitor 4K | B22: 47 | C22: 4465000 | D22: 243
A23: Mouse Ergo | B23: 51 | C23: 918000 | D23: 286
A24: SmartPhone X | B24: 65 | C24: 14300000 | D24: 426
A25: Tablet Air | B25: 51 | C25: 9180000 | D25: 385
A26: Webcam HD | B26: 46 | C26: 1012000 | D26: 340
A27: Wireless Earbuds | B27: 36 | C27: 1260000 | D27: 249
A28: Grand Total | B28: 426 | C28: 71067000 | D28: 2867
A30: Monthly Revenue By Channel
A31: Total Revenue | B31: Column Labels
A32: Row Labels | B32: Distributor | C32: In-Store | D32: Online | E32: N/A | F32: Grand Total
A33: January | B33: 8653200 | C33: 16532100 | D33: 24450500 | F33: 49635800
A34: February | B34: 13359400 | C34: 5095750 | D34: 2169000 | F34: 20624150
A35: March | B35: 6368600 | C35: 28919750 | D35: 18531250 | F35: 53819600
A36: April | B36: 8246100 | C36: 19848000 | D36: 9866400 | F36: 37960500
A37: May | B37: 1829100 | C37: 5428500 | D37: 10338050 | E37: 1980000 | F37: 19575650
A38: June | B38: 11848000 | C38: 17334250 | D38: 11462000 | F38: 40644250
A39: July | B39: 13660400 | C39: 14699000 | D39: 6467000 | E39: 88000 | F39: 34914400
A40: August | B40: 11542100 | C40: 33716650 | D40: 1437100 | F40: 46695850
A41: September | B41: 4538400 | C41: 13445750 | D41: 17868600 | F41: 35852750
A42: October | B42: 5972000 | C42: 21199500 | D42: 27060500 | F42: 54232000
A43: November | B43: 4191500 | C43: 9371000 | D43: 13341500 | E43: 1760000 | F43: 28664000
A44: December | B44: 9758200 | C44: 16676800 | D44: 13848350 | F44: 40283350
A45: Grand Total | B45: 99967000 | C45: 202267050 | D45: 156840250 | E45: 3828000 | F45: 462902300

Sheet Clean Raw Data
A1: Order ID | B1: Order Date | C1: Customer ID | D1: Sales Rep | E1: Region | F1: Product | G1: Category | H1: Channel | I1: Quantity | J1: Unit Price (₦) | K1: Unit Price Clean | L1: Revenue | M1: Discount (%) | N1: Discount | O1: Net Revenue | P1: Status | Q1: Product_Clean | R1: Category_Clean | S1: Channel_Clean
A2: ORD-47512 | B2: 45434 | C2: CUST-4094 | D2: Yemi Osinbajo | E2: East | F2: Wireless Earbuds | G2: Accessories | H2: Distributor | I2: 7 | J2: 35000 | K2: =J2 -> 35000 | L2: =I2*K2 -> 245000 | M2: 10 | N2: =M2/100 * L2 -> 24500 | O2: =L2-N2 -> 220500 | P2: Pending | Q2: Wireless Earbuds | R2: Accessories | S2: Distributor
A3: ORD-67431 | B3: 45464 | C3: CUST-1447 | D3: Fatima Aliyu | E3: North | F3: Mouse Ergo | G3: Accessories | H3: Distributor | I3: 4 | J3: 18000 | K3: =J3 -> 18000 | L3: =I3*K3 -> 72000 | M3: 0 | N3: =M3/100 * L3 -> 0 | O3: =L3-N3 -> 72000 | P3: Completed | Q3: Mouse Ergo | R3: Accessories | S3: Distributor
A4: ORD-89777 | B4: 45513 | C4: CUST-4674 | D4: James Okafor | E4: West | F4: Keyboard Mech | G4: Accessories | H4: Distributor | I4: 2 | J4: 28000 | K4: =J4 -> 28000 | L4: =I4*K4 -> 56000 | M4: 15 | N4: =M4/100 * L4 -> 8400 | O4: =L4-N4 -> 47600 | P4: Pending | Q4: Keyboard Mech | R4: Accessories | S4: Distributor
A5: ORD-84141 | B5: 45573 | C5: CUST-1120 | D5: Fatima Aliyu | E5: West | F5: Webcam HD | G5: Accessories | H5: Distributor | I5: 1 | J5: 22000 | K5: =J5 -> 22000 | L5: =I5*K5 -> 22000 | M5: 0 | N5: =M5/100 * L5 -> 0 | O5: =L5-N5 -> 22000 | P5: Completed | Q5: Webcam HD | R5: Accessories | S5: Distributor
A6: ORD-72684 | B6: 45492 | C6: CUST-2977 | D6: Chukwudi Eze | E6: North | F6: Keyboard Mech | G6: Accessories | H6: In-Store | I6: 6 | J6: 28000 | K6: =J6 -> 28000 | L6: =I6*K6 -> 168000 | M6: 0 | N6: =M6/100 * L6 -> 0 | O6: =L6-N6 -> 168000 | P6: Completed | Q6: Keyboard Mech | R6: Accessories | S6: In-Store
A7: ORD-88636 | B7: 45604 | C7: CUST-1008 | D7: Fatima Aliyu | E7: South | F7: Mouse Ergo | G7: Accessories | H7: Online | I7: 4 | J7: 18000 | K7: =J7 -> 18000 | L7: =I7*K7 -> 72000 | M7: 20 | N7: =M7/100 * L7 -> 14400 | O7: =L7-N7 -> 57600 | P7: Completed | Q7: Mouse Ergo | R7: Accessories | S7: Online
A8: ORD-98754 | B8: 45488 | C8: CUST-1949 | D8: Ngozi Adeyemi | E8: North | F8: Tablet Air | G8: Electronics | H8: In-Store | I8: 11 | J8: 180000 | K8: =J8 -> 180000 | L8: =I8*K8 -> 1980000 | M8: 10 | N8: =M8/100 * L8 -> 198000 | O8: =L8-N8 -> 1782000 | P8: Completed | Q8: Tablet Air | R8: Electronics | S8: In-Store
A9: ORD-27224 | B9: 45547 | C9: CUST-3174 | D9: Emeka Nwosu | E9: East | F9: SmartPhone X | G9: Electronics | H9: Online | I9: 7 | J9: 220000 | K9: =J9 -> 220000 | L9: =I9*K9 -> 1540000 | M9: 0 | N9: =M9/100 * L9 -> 0 | O9: =L9-N9 -> 1540000 | P9: Completed | Q9: SmartPhone X | R9: Electronics | S9: Online
A10: ORD-64948 | B10: 45478 | C10: CUST-3751 | D10: Fatima Aliyu | E10: East | F10: Webcam HD | G10: Accessories | H10: In-Store | I10: 8 | J10: 22000 | K10: =J10 -> 22000 | L10: =I10*K10 -> 176000 | M10: 0 | N10: =M10/100 * L10 -> 0 | O10: =L10-N10 -> 176000 | P10: Cancelled | Q10: Webcam HD | R10: Accessories | S10: In-Store
A11: ORD-68459 | B11: 45491 | C11: CUST-2962 | D11: N/A | E11: N/A | F11: Tablet Air | G11: Electronics | H11: In-Store | I11: 10 | J11: 180000 | K11: =J11 -> 180000 | L11: =I11*K11 -> 1800000 | M11: 5 | N11: =M11/100 * L11 -> 90000 | O11: =L11-N11 -> 1710000 | P11: Pending | Q11: Tablet Air | R11: Electronics | S11: In-Store
A12: ORD-26406 | B12: 45357 | C12: CUST-3698 | D12: Yemi Osinbajo | E12: North | F12: Laptop Pro | G12: Electronics | H12: Online | I12: 19 | J12: 450000 | K12: =J12 -> 450000 | L12: =I12*K12 -> 8550000 | M12: 10 | N12: =M12/100 * L12 -> 855000 | O12: =L12-N12 -> 7695000 | P12: Completed | Q12: Laptop Pro | R12: Electronics | S12: Online
A13: ORD-99016 | B13: 45304 | C13: CUST-3424 | D13: Chukwudi Eze | E13: East | F13: Keyboard Mech | G13: Accessories | H13: Online | I13: 20 | J13: 28000 | K13: =J13 -> 28000 | L13: =I13*K13 -> 560000 | M13: 10 | N13: =M13/100 * L13 -> 56000 | O13: =L13-N13 -> 504000 | P13: Completed | Q13: Keyboard Mech | R13: Accessories | S13: Online
... A82: ORD-74451 | B82: 45350 | C82: CUST-1658 | D82: Kemi Adebayo | E82: East | F82: SmartPhone X | G82: Electronics | H82: online | I82: 11 | J82: 220000 | K82: =J82 -> 220000 | L82: =I82*K82 -> 2420000 | M82: 15 | N82: =M82/100 * L82 -> 363000 | O82: =L82-N82 -> 2057000 | P82: Cancelled | Q82: SmartPhone X | R82: Electronics | S82: online
A83: ORD-96772 | B83: 45415 | C83: CUST-2939 | D83: Ngozi Adeyemi | E83: North | F83: Mouse Ergo | G83: Accessories | H83: online | I83: 6 | J83: 1 | K83: 18000 | L83: =I83*K83 -> 108000 | M83: 15 | N83: =M83/100 * L83 -> 16200 | O83: =L83-N83 -> 91800 | P83: Pending | Q83: Mouse Ergo | R83: Accessories | S83: online
A84: ORD-52291 | B84: 45614 | C84: CUST-2124 | D84: Fatima Aliyu | E84: North | F84: Wireless Earbuds | G84: Accessories | H84: Distributor | I84: 9 | J84: 35000 | K84: =J84 -> 35000 | L84: =I84*K84 -> 315000 | M84: 0 | N84: =M84/100 * L84 -> 0 | O84: =L84-N84 -> 315000 | P84: Completed | Q84: Wireless Earbuds | R84: Accessories | S84: Distributor
A85: ORD-93748 | B85: 45405 | C85: CUST-1588 | D85: Amaka Bello | E85: North | F85: Mouse Ergo | G85: Accessories | H85: Online | I85: 17 | J85: 18000 | K85: =J85 -> 18000 | L85: =I85*K85 -> 306000 | M85: 10 | N85: =M85/100 * L85 -> 30600 | O85: =L85-N85 -> 275400 | P85: Completed | Q85: Mouse Ergo | R85: Accessories | S85: Online
A86: ORD-63090 | B86: 45572 | C86: CUST-2841 | D86: Chukwudi Eze | E86: South | F86: Tablet Air | G86: Electronics | H86: Online | I86: 1 | J86: 180000 | K86: =J86 -> 180000 | L86: =I86*K86 -> 180000 | M86: 15 | N86: =M86/100 * L86 -> 27000 | O86: =L86-N86 -> 153000 | P86: Completed | Q86: Tablet Air | R86: Electronics | S86: Online
A87: ORD-99764 | B87: 45640 | C87: CUST-3477 | D87: Ngozi Adeyemi | E87: South | F87: SmartPhone X | G87: Electronics | H87: Distributor | I87: 11 | J87: 220000 | K87: =J87 -> 220000 | L87: =I87*K87 -> 2420000 | M87: 0 | N87: =M87/100 * L87 -> 0 | O87: =L87-N87 -> 2420000 | P87: Completed | Q87: SmartPhone X | R87: Electronics | S87: Distributor
A88: ORD-45358 | B88: 45552 | C88: CUST-2671 | D88: Chukwudi Eze | E88: North | F88: SmartPhone X | G88: Electronics | H88: In-Store | I88: 15 | J88: 220000 | K88: =J88 -> 220000 | L88: =I88*K88 -> 3300000 | M88: 10 | N88: =M88/100 * L88 -> 330000 | O88: =L88-N88 -> 2970000 | P88: Completed | Q88: SmartPhone X | R88: Electronics | S88: In-Store
A89: ORD-12872 | B89: 45437 | C89: CUST-3190 | D89: Chukwudi Eze | E89: North | F89: Webcam HD | G89: Accessories | H89: Distributor | I89: 13 | J89: 22000 | K89: =J89 -> 22000 | L89: =I89*K89 -> 286000 | M89: 15 | N89: =M89/100 * L89 -> 42900 | O89: =L89-N89 -> 243100 | P89: Completed | Q89: Webcam HD | R89: Accessories | S89: Distributor
A90: ORD-63271 | B90: 45294 | C90: CUST-2205 | D90: Tunde Fashola | E90: East | F90: Mouse Ergo | G90: Accessories | H90: In-Store | I90: 16 | J90: 18000 | K90: =J90 -> 18000 | L90: =I90*K90 -> 288000 | M90: 5 | N90: =M90/100 * L90 -> 14400 | O90: =L90-N90 -> 273600 | P90: Completed | Q90: Mouse Ergo | R90: Accessories | S90: In-Store
A91: ORD-41133 | B91: 45438 | C91: CUST-4212 | D91: Yemi Osinbajo | E91: East | F91: Mouse Ergo | G91: Accessories | H91: Online | I91: 18 | J91: 18000 | K91: =J91 -> 18000 | L91: =I91*K91 -> 324000 | M91: 0 | N91: =M91/100 * L91 -> 0 | O91: =L91-N91 -> 324000 | P91: Pending | Q91: Mouse Ergo | R91: Accessories | S91: Online
A92: ORD-61773 | B92: 45360 | C92: CUST-2146 | D92: James Okafor | E92: West | F92: Mouse Ergo | G92: Accessories | H92: Online | I92: 12 | J92: 18000 | K92: =J92 -> 18000 | L92: =I92*K92 -> 216000 | M92: 0 | N92: =M92/100 * L92 -> 0 | O92: =L92-N92 -> 216000 | P92: Completed | Q92: Mouse Ergo | R92: Accessories | S92: On-Line
A93: ORD-75333 | B93: 45475 | C93: CUST-3282 | D93: Fatima Aliyu | E93: North | F93: Mouse Ergo | G93: Accessories | H93: Online | I93: 4 | J93: 18000 | K93: =J93 -> 18000 | L93: =I93*K93 -> 72000 | M93: 5 | N93: =M93/100 * L93 -> 3600 | O93: =L93-N93 -> 68400 | P93: Completed | Q93: Mouse Ergo | R93: Accessories | S93: Online
A94: ORD-87621 | B94: 45652 | C94: CUST-4260 | D94: Ibrahim Musa | E94: North | F94: Keyboard Mech | G94: Accessories | H94: In-Store | I94: 9 | J94: 28000 | K94: =J94 -> 28000 | L94: =I94*K94 -> 252000 | M94: 20 | N94: =M94/100 * L94 -> 50400 | O94: =L94-N94 -> 201600 | P94: Pending | Q94: Keyboard Mech | R94: Accessories | S94: In-Store
A95: ORD-24996 | B95: 45517 | C95: CUST-2703 | D95: Ngozi Adeyemi | E95: West | F95: Webcam HD | G95: Accessories | H95: Online | I95: 14 | J95: 22000 | K95: =J95 -> 22000 | L95: =I95*K95 -> 308000 | M95: 0 | N95: =M95/100 * L95 -> 0 | O95: =L95-N95 -> 308000 | P95: Pending | Q95: Webcam HD | R95: Accessories | S95: Online
... A120: ORD-64732 | B120: 45398 | C120: CUST-3255 | D120: Chukwudi Eze | E120: South | F120: Laptop Pro | G120: Electronics | H120: Distributor | I120: 13 | J120: 450000 | K120: =J120 -> 450000 | L120: =I120*K120 -> 5850000 | M120: 10 | N120: =M120/100 * L120 -> 585000 | O120: =L120-N120 -> 5265000 | P120: Pending | Q120: Laptop Pro | R120: Electronics | S120: Distributor
A121: ORD-41278 | B121: 45567 | C121: CUST-2266 | D121: Ngozi Adeyemi | E121: North | F121: Laptop Pro | G121: Electronics | H121: Online | I121: 15 | J121: -5000 | K121: 450000 | L121: =I121*K121 -> 6750000 | M121: 10 | N121: =M121/100 * L121 -> 675000 | O121: =L121-N121 -> 6075000 | P121: Completed | Q121: Laptop Pro | R121: Electronics | S121: Online
A122: ORD-25572 | B122: 45358 | C122: CUST-3467 | D122: Amaka Bello | E122: West | F122: Tablet Air | G122: Electronics | H122: Distributor | I122: 18 | J122: 180000 | K122: =J122 -> 180000 | L122: =I122*K122 -> 3240000 | M122: 0 | N122: =M122/100 * L122 -> 0 | O122: =L122-N122 -> 3240000 | P122: Cancelled | Q122: Tablet Air | R122: Electronics | S122: Distributor
A123: ORD-46002 | B123: 45293 | C123: CUST-2510 | D123: Fatima Aliyu | E123: North | F123: Laptop Pro | G123: Electronics | H123: Online | I123: 15 | J123: 450000 | K123: =J123 -> 450000 | L123: =I123*K123 -> 6750000 | M123: 5 | N123: =M123/100 * L123 -> 337500 | O123: =L123-N123 -> 6412500 | P123: Returned | Q123: Laptop Pro | R123: Electronics | S123: Online
A124: ORD-96752 | B124: 45644 | C124: CUST-1249 | D124: Chukwudi Eze | E124: South | F124: Mouse Ergo | G124: Accessories | H124: Distributor | I124: 2 | J124: 18000 | K124: =J124 -> 18000 | L124: =I124*K124 -> 36000 | M124: 10 | N124: =M124/100 * L124 -> 3600 | O124: =L124-N124 -> 32400 | P124: Pending | Q124: Mouse Ergo | R124: Accessories | S124: Distributor
A125: ORD-46512 | B125: 45635 | C125: CUST-1118 | D125: Ibrahim Musa | E125: East | F125: Wireless Earbuds | G125: Accessories | H125: In-Store | I125: 20 | J125: 35000 | K125: =J125 -> 35000 | L125: =I125*K125 -> 700000 | M125: 15 | N125: =M125/100 * L125 -> 105000 | O125: =L125-N125 -> 595000 | P125: Completed | Q125: Wireless Earbuds | R125: Accessories | S125: In-Store
A126: ORD-35415 | B126: 45419 | C126: CUST-1710 | D126: Fatima Aliyu | E126: South | F126: Monitor 4K | G126: Electronics | H126: In-Store | I126: 4 | J126: 95000 | K126: =J126 -> 95000 | L126: =I126*K126 -> 380000 | M126: 0 | N126: =M126/100 * L126 -> 0 | O126: =L126-N126 -> 380000 | P126: Pending | Q126: Monitor 4K | R126: Electronics | S126: In-Store
A127: ORD-43980 | B127: 45482 | C127: CUST-3145 | D127: Fatima Aliyu | E127: South | F127: Tablet Air | G127: Electronics | H127: Distributor | I127: 1 | J127: 180000 | K127: =J127 -> 180000 | L127: =I127*K127 -> 180000 | M127: 0 | N127: =M127/100 * L127 -> 0 | O127: =L127-N127 -> 180000 | P127: Completed | Q127: Tablet Air | R127: Electronics | S127: Distributor
A128: ORD-86344 | B128: 45337 | C128: CUST-2256 | D128: Emeka Nwosu | E128: South | F128: Laptop Pro | G128: Electronics | H128: Distributor | I128: 2 | J128: 450000 | K128: =J128 -> 450000 | L128: =I128*K128 -> 900000 | M128: 15 | N128: =M128/100 * L128 -> 135000 | O128: =L128-N128 -> 765000 | P128: Pending | Q128: Laptop Pro | R128: Electronics | S128: Distributor
A129: ORD-62550 | B129: 45550 | C129: CUST-1032 | D129: Kemi Adebayo | E129: East | F129: SmartPhone X | G129: Electronics | H129: Distributor | I129: 11 | J129: 220000 | K129: =J129 -> 220000 | L129: =I129*K129 -> 2420000 | M129: 0 | N129: =M129/100 * L129 -> 0 | O129: =L129-N129 -> 2420000 | P129: Returned | Q129: SmartPhone X | R129: Electronics | S129: Distributor
A130: ORD-67014 | B130: 45637 | C130: CUST-2302 | D130: Ngozi Adeyemi | E130: East | F130: Tablet Air | G130: Electronics | H130: Distributor | I130: 13 | J130: 180000 | K130: =J130 -> 180000 | L130: =I130*K130 -> 2340000 | M130: 15 | N130: =M130/100 * L130 -> 351000 | O130: =L130-N130 -> 1989000 | P130: Cancelled | Q130: Tablet Air | R130: Electronics | S130: Distributor
A131: ORD-67261 | B131: 45592 | C131: CUST-1718 | D131: Fatima Aliyu | E131: South | F131: Mouse Ergo | G131: Accessories | H131: In-Store | I131: 8 | J131: 18000 | K131: =J131 -> 18000 | L131: =I131*K131 -> 144000 | M131: 15 | N131: =M131/100 * L131 -> 21600 | O131: =L131-N131 -> 122400 | P131: Cancelled | Q131: Mouse Ergo | R131: Accessories | S131: In-Store
A132: ORD-59797 | B132: 45522 | C132: CUST-1511 | D132: Fatima Aliyu | E132: East | F132: SmartPhone X | G132: Electronics | H132: Distributor | I132: 2 | J132: 220000 | K132: =J132 -> 220000 | L132: =I132*K132 -> 440000 | M132: 15 | N132: =M132/100 * L132 -> 66000 | O132: =L132-N132 -> 374000 | P132: Returned | Q132: SmartPhone X | R132: Electronics | S132: Distributor
A133: ORD-87847 | B133: 45579 | C133: CUST-2496 | D133: Tunde Fashola | E133: North | F133: SmartPhone X | G133: Electronics | H133: Distributor | I133: 5 | J133: 220000 | K133: =J133 -> 220000 | L133: =I133*K133 -> 1100000 | M133: 5 | N133: =M133/100 * L133 -> 55000 | O133: =L133-N133 -> 1045000 | P133: Cancelled | Q133: SmartPhone X | R133: Electronics | S133: Distributor
... A147: ORD-27125 | B147: 45433 | C147: CUST-2287 | D147: Kemi Adebayo | E147: North | F147: Mouse Ergo | G147: Accessories | H147: Online | I147: 2 | J147: 18000 | K147: =J147 -> 18000 | L147: =I147*K147 -> 36000 | M147: 0 | N147: =M147/100 * L147 -> 0 | O147: =L147-N147 -> 36000 | P147: Completed | Q147: Mouse Ergo | R147: Accessories | S147: Online
A148: ORD-80852 | B148: 45445 | C148: CUST-1400 | D148: Ibrahim Musa | E148: East | F148: Monitor 4K | G148: Electronics | H148: In-Store | I148: 17 | J148: 1 | K148: 95000 | L148: =I148*K148 -> 1615000 | M148: 15 | N148: =M148/100 * L148 -> 242250 | O148: =L148-N148 -> 1372750 | P148: Completed | Q148: Monitor 4K | R148: Electronics | S148: In-Store
A149: ORD-81258 | B149: 45516 | C149: CUST-4738 | D149: Ibrahim Musa | E149: East | F149: Laptop Pro | G149: Electronics | H149: Distributor | I149: 18 | J149: 450000 | K149: =J149 -> 450000 | L149: =I149*K149 -> 8100000 | M149: 20 | N149: =M149/100 * L149 -> 1620000 | O149: =L149-N149 -> 6480000 | P149: Completed | Q149: Laptop Pro | R149: Electronics | S149: Distributor
A150: ORD-11620 | B150: 45558 | C150: CUST-3869 | D150: Yemi Osinbajo | E150: South | F150: Webcam HD | G150: Accessories | H150: In-Store | I150: 11 | J150: 22000 | K150: =J150 -> 22000 | L150: =I150*K150 -> 242000 | M150: 10 | N150: =M150/100 * L150 -> 24200 | O150: =L150-N150 -> 217800 | P150: Pending | Q150: Webcam HD | R150: Accessories | S150: In-Store
A151: ORD-99070 | B151: 45476 | C151: CUST-1475 | D151: Chukwudi Eze | E151: East | F151: Webcam HD | G151: Accessories | H151: N/A | I151: 4 | J151: 22000 | K151: =J151 -> 22000 | L151: =I151*K151 -> 88000 | M151: 0 | N151: =M151/100 * L151 -> 0 | O151: =L151-N151 -> 88000 | P151: Completed | Q151: Webcam HD | R151: Accessories | S151: None
A152: ORD-80329 | B152: 45604 | C152: CUST-2931 | D152: Kemi Adebayo | E152: East | F152: SmartPhone X | G152: Electronics | H152: Distributor | I152: 12 | J152: 220000 | K152: =J152 -> 220000 | L152: =I152*K152 -> 2640000 | M152: 0 | N152: =M152/100 * L152 -> 0 | O152: =L152-N152 -> 2640000 | P152: Completed | Q152: SmartPhone X | R152: Electronics | S152: Distributor
A153: ORD-89807 | B153: 45299 | C153: CUST-2719 | D153: Ibrahim Musa | E153: North | F153: Webcam HD | G153: Accessories | H153: Distributor | I153: 10 | J153: 22000 | K153: =J153 -> 22000 | L153: =I153*K153 -> 220000 | M153: 0 | N153: =M153/100 * L153 -> 0 | O153: =L153-N153 -> 220000 | P153: Pending | Q153: Webcam HD | R153: Accessories | S153: Distributor
A154: ORD-51104 | B154: 45350 | C154: CUST-1761 | D154: James Okafor | E154: North | F154: Laptop Pro | G154: Electronics | H154: Online | I154: 2 | J154: 450000 | K154: =J154 -> 450000 | L154: =I154*K154 -> 900000 | M154: 10 | N154: =M154/100 * L154 -> 90000 | O154: =L154-N154 -> 810000 | P154: Completed | Q154: Laptop Pro | R154: Electronics | S154: Online
A155: ORD-16734 | B155: 45586 | C155: CUST-3811 | D155: Kemi Adebayo | E155: North | F155: Laptop Pro | G155: Electronics | H155: Online | I155: 16 | J155: 450000 | K155: =J155 -> 450000 | L155: =I155*K155 -> 7200000 | M155: 0 | N155: =M155/100 * L155 -> 0 | O155: =L155-N155 -> 7200000 | P155: Completed | Q155: Laptop Pro | R155: Electronics | S155: Online
A156: ORD-14852 | B156: 45550 | C156: CUST-1062 | D156: Tunde Fashola | E156: North | F156: Tablet Air | G156: Electronics | H156: Distributor | I156: 15 | J156: 180000 | K156: =J156 -> 180000 | L156: =I156*K156 -> 2700000 | M156: 0 | N156: =M156/100 * L156 -> 0 | O156: =L156-N156 -> 2700000 | P156: Completed | Q156: Tablet Air | R156: Electronics | S156: Distributor
A157: ORD-25328 | B157: 45370 | C157: CUST-2571 | D157: Fatima Aliyu | E157: South | F157: Tablet Air | G157: Electronics | H157: In-Store | I157: 14 | J157: 180000 | K157: =J157 -> 180000 | L157: =I157*K157 -> 2520000 | M157: 10 | N157: =M157/100 * L157 -> 252000 | O157: =L157-N157 -> 2268000 | P157: Completed | Q157: Tablet Air | R157: Electronics | S157: In-Store
A158: ORD-18981 | B158: 45311 | C158: CUST-1335 | D158: Ngozi Adeyemi | E158: West | F158: SmartPhone X | G158: Electronics | H158: Online | I158: 19 | J158: 220000 | K158: =J158 -> 220000 | L158: =I158*K158 -> 4180000 | M158: 10 | N158: =M158/100 * L158 -> 418000 | O158: =L158-N158 -> 3762000 | P158: Pending | Q158: SmartPhone X | R158: Electronics | S158: Online
A159: ORD-71487 | B159: 45369 | C159: CUST-4851 | D159: Yemi Osinbajo | E159: North | F159: Mouse Ergo | G159: Accessories | H159: Online | I159: 9 | J159: 18000 | K159: =J159 -> 18000 | L159: =I159*K159 -> 162000 | M159: 0 | N159: =M159/100 * L159 -> 0 | O159: =L159-N159 -> 162000 | P159: Completed | Q159: Mouse Ergo | R159: Accessories | S159: Online
A160: ORD-46877 | B160: 45336 | C160: CUST-1548 | D160: Yemi Osinbajo | E160: East | F160: Mouse Ergo | G160: Accessories | H160: ONLINE | I160: 18 | J160: 18000 | K160: =J160 -> 18000 | L160: =I160*K160 -> 324000 | M160: 0 | N160: =M160/100 * L160 -> 0 | O160: =L160-N160 -> 324000 | P160: Returned | Q160: Mouse Ergo | R160: Accessories | S160: ONLINE
A161: ORD-72580 | B161: 45423 | C161: CUST-2236 | D161: Ngozi Adeyemi | E161: North | F161: Monitor 4K | G161: Electronics | H161: Distributor | I161: 8 | J161: 95000 | K161: =J161 -> 95000 | L161: =I161*K161 -> 760000 | M161: 5 | N161: =M161/100 * L161 -> 38000 | O161: =L161-N161 -> 722000 | P161: Completed | Q161: Monitor 4K | R161: Electronics | S161: Distributor
A162: ORD-67154 | B162: 45344 | C162: CUST-4771 | D162: Tunde Fashola | E162: East | F162: Laptop Pro | G162: Electronics | H162: In-Store | I162: 12 | J162: -5000 | K162: 450000 | L162: =I162*K162 -> 5400000 | M162: 5 | N162: =M162/100 * L162 -> 270000 | O162: =L162-N162 -> 5130000 | P162: Pending | Q162: Laptop Pro | R162: Electronics | S162: In-Store
A163: ORD-33496 | B163: 45544 | C163: CUST-4339 | D163: Amaka Bello | E163: North | F163: SmartPhone X | G163: Electronics | H163: In-Store | I163: 7 | J163: 220000 | K163: =J163 -> 220000 | L163: =I163*K163 -> 1540000 | M163: 10 | N163: =M163/100 * L163 -> 154000 | O163: =L163-N163 -> 1386000 | P163: Pending | Q163: SmartPhone X | R163: Electronics | S163: In-Store
A164: ORD-61498 | B164: 45332 | C164: CUST-4374 | D164: Kemi Adebayo | E164: south | F164: Webcam HD | G164: Accessories | H164: Online | I164: 1 | J164: 22000 | K164: =J164 -> 22000 | L164: =I164*K164 -> 22000 | M164: 5 | N164: =M164/100 * L164 -> 1100 | O164: =L164-N164 -> 20900 | P164: Cancelled | Q164: Webcam HD | R164: Accessories | S164: On-Line
A165: ORD-64090 | B165: 45393 | C165: CUST-3648 | D165: Tunde Fashola | E165: North | F165: Keyboard Mech | G165: Accessories | H165: In-Store | I165: 8 | J165: 28000 | K165: =J165 -> 28000 | L165: =I165*K165 -> 224000 | M165: 0 | N165: =M165/100 * L165 -> 0 | O165: =L165-N165 -> 224000 | P165: Completed | Q165: Keyboard Mech | R165: Accessories | S165: In-Store
A166: ORD-71918 | B166: 45520 | C166: CUST-3664 | D166: Chukwudi Eze | E166: East | F166: SmartPhone X | G166: Electronics | H166: In-Store | I166: 14 | J166: 220000 | K166: =J166 -> 220000 | L166: =I166*K166 -> 3080000 | M166: 15 | N166: =M166/100 * L166 -> 462000 | O166: =L166-N166 -> 2618000 | P166: Completed | Q166: SmartPhone X | R166: Electronics | S166: In-Store
A167: ORD-92614 | B167: 45403 | C167: CUST-2816 | D167: Yemi Osinbajo | E167: North | F167: SmartPhone X | G167: Electronics | H167: Distributor | I167: 1 | J167: 220000 | K167: =J167 -> 220000 | L167: =I167*K167 -> 220000 | M167: 0 | N167: =M167/100 * L167 -> 0 | O167: =L167-N167 -> 220000 | P167: Completed | Q167: SmartPhone X | R167: Electronics | S167: Distributor
A168: ORD-20237 | B168: 45357 | C168: CUST-2343 | D168: James Okafor | E168: East | F168: SmartPhone X | G168: Electronics | H168: In-Store | I168: 19 | J168: 220000 | K168: =J168 -> 220000 | L168: =I168*K168 -> 4180000 | M168: 10 | N168: =M168/100 * L168 -> 418000 | O168: =L168-N168 -> 3762000 | P168: Pending | Q168: SmartPhone X | R168: Electronics | S168: In-Store
A169: ORD-87662 | B169: 45370 | C169: CUST-4884 | D169: Fatima Aliyu | E169: North | F169: Monitor 4K | G169: Electronics | H169: Online | I169: 19 | J169: 95000 | K169: =J169 -> 95000 | L169: =I169*K169 -> 1805000 | M169: 10 | N169: =M169/100 * L169 -> 180500 | O169: =L169-N169 -> 1624500 | P169: Cancelled | Q169: Monitor 4K | R169: Electronics | S169: Online
A170: ORD-30934 | B170: 45573 | C170: CUST-1897 | D170: Tunde Fashola | E170: South | F170: Keyboard Mech | G170: Accessories | H170: Distributor | I170: 10 | J170: 28000 | K170: =J170 -> 28000 | L170: =I170*K170 -> 280000 | M170: 0 | N170: =M170/100 * L170 -> 0 | O170: =L170-N170 -> 280000 | P170: Completed | Q170: Keyboard Mech | R170: Accessories | S170: Distributor
A171: ORD-18819 | B171: 45304 | C171: CUST-2797 | D171: Yemi Osinbajo | E171: North | F171: SmartPhone X | G171: Electronics | H171: Online | I171: 8 | J171: 220000 | K171: =J171 -> 220000 | L171: =I171*K171 -> 1760000 | M171: 15 | N171: =M171/100 * L171 -> 264000 | O171: =L171-N171 -> 1496000 | P171: Completed | Q171: SmartPhone X | R171: Electronics | S171: Online
A172: ORD-81482 | B172: 45399 | C172: CUST-3465 | D172: Yemi Osinbajo | E172: West | F172: SmartPhone X | G172: Electronics | H172: Online | I172: 3 | J172: 220000 | K172: =J172 -> 220000 | L172: =I172*K172 -> 660000 | M172: 0 | N172: =M172/100 * L172 -> 0 | O172: =L172-N172 -> 660000 | P172: Completed | Q172: SmartPhone X | R172: Electronics | S172: Online
A173: ORD-98805 | B173: 45387 | C173: CUST-1174 | D173: Amaka Bello | E173: East | F173: Tablet Air | G173: Electronics | H173: Online | I173: 6 | J173: 180000 | K173: =J173 -> 180000 | L173: =I173*K173 -> 1080000 | M173: 0 | N173: =M173/100 * L173 -> 0 | O173: =L173-N173 -> 1080000 | P173: Completed | Q173: Tablet Air | R173: Electronics | S173: Online
A174: ORD-38047 | B174: 45589 | C174: CUST-3403 | D174: Tunde Fashola | E174: East | F174: Wireless Earbuds | G174: Accessories | H174: In-Store | I174: 5 | J174: 35000 | K174: =J174 -> 35000 | L174: =I174*K174 -> 175000 | M174: 0 | N174: =M174/100 * L174 -> 0 | O174: =L174-N174 -> 175000 | P174: Returned | Q174: Wireless Earbuds | R174: Accessories | S174: In-Store
... A185: ORD-33260 | B185: 45563 | C185: CUST-2494 | D185: James Okafor | E185: North | F185: Monitor 4K | G185: Electronics | H185: In-Store | I185: 4 | J185: 95000 | K185: =J185 -> 95000 | L185: =I185*K185 -> 380000 | M185: 20 | N185: =M185/100 * L185 -> 76000 | O185: =L185-N185 -> 304000 | P185: Completed | Q185: Monitor 4K | R185: Electronics | S185: In-Store
A186: ORD-40161 | B186: 45628 | C186: CUST-2786 | D186: Tunde Fashola | E186: East | F186: Webcam HD | G186: Accessories | H186: Distributor | I186: 13 | J186: 999999999 | K186: 22000 | L186: =I186*K186 -> 286000 | M186: 20 | N186: =M186/100 * L186 -> 57200 | O186: =L186-N186 -> 228800 | P186: COMPLETED | Q186: Webcam HD | R186: Accessories | S186: Distributor
A187: ORD-40715 | B187: 45409 | C187: CUST-4753 | D187: Ngozi Adeyemi | E187: East | F187: Webcam HD | G187: Accessories | H187: Online | I187: 17 | J187: 22000 | K187: =J187 -> 22000 | L187: =I187*K187 -> 374000 | M187: 0 | N187: =M187/100 * L187 -> 0 | O187: =L187-N187 -> 374000 | P187: Completed | Q187: Webcam HD | R187: Accessories | S187: Online
A188: ORD-56437 | B188: 45420 | C188: CUST-4856 | D188: Yemi Osinbajo | E188: West | F188: Laptop Pro | G188: Electronics | H188: In-Store | I188: 9 | J188: 450000 | K188: =J188 -> 450000 | L188: =I188*K188 -> 4050000 | M188: 10 | N188: =M188/100 * L188 -> 405000 | O188: =L188-N188 -> 3645000 | P188: Pending | Q188: Laptop Pro | R188: Electronics | S188: In-Store
A189: ORD-38074 | B189: 45440 | C189: CUST-4228 | D189: Kemi Adebayo | E189: South | F189: Monitor 4K | G189: Electronics | H189: In-Store | I189: 5 | J189: 95000 | K189: =J189 -> 95000 | L189: =I189*K189 -> 475000 | M189: 0 | N189: =M189/100 * L189 -> 0 | O189: =L189-N189 -> 475000 | P189: Completed | Q189: Monitor 4K | R189: Electronics | S189: In-Store
A190: ORD-53228 | B190: 45452 | C190: CUST-2324 | D190: Kemi Adebayo | E190: East | F190: Keyboard Mech | G190: Accessories | H190: Online | I190: 15 | J190: 28000 | K190: =J190 -> 28000 | L190: =I190*K190 -> 420000 | M190: 0 | N190: =M190/100 * L190 -> 0 | O190: =L190-N190 -> 420000 | P190: Completed | Q190: Keyboard Mech | R190: Accessories | S190: Online
A191: ORD-25191 | B191: 45524 | C191: CUST-2098 | D191: James Okafor | E191: North | F191: SmartPhone X | G191: Electronics | H191: In-Store | I191: 11 | J191: 220000 | K191: =J191 -> 220000 | L191: =I191*K191 -> 2420000 | M191: 0 | N191: =M191/100 * L191 -> 0 | O191: =L191-N191 -> 2420000 | P191: Completed | Q191: SmartPhone X | R191: Electronics | S191: In-Store
A192: ORD-74054 | B192: 45420 | C192: CUST-3202 | D192: Amaka Bello | E192: North | F192: Tablet Air | G192: Electronics | H192: Online | I192: 10 | J192: 180000 | K192: =J192 -> 180000 | L192: =I192*K192 -> 1800000 | M192: 0 | N192: =M192/100 * L192 -> 0 | O192: =L192-N192 -> 1800000 | P192: Pending | Q192: Tablet Air | R192: Electronics | S192: Online
A193: ORD-21188 | B193: 45583 | C193: CUST-3300 | D193: Ibrahim Musa | E193: North | F193: SmartPhone X | G193: Electronics | H193: Distributor | I193: 18 | J193: 220000 | K193: =J193 -> 220000 | L193: =I193*K193 -> 3960000 | M193: 0 | N193: =M193/100 * L193 -> 0 | O193: =L193-N193 -> 3960000 | P193: Completed | Q193: SmartPhone X | R193: Electronics | S193: Distributor
A194: ORD-74066 | B194: 45436 | C194: CUST-4403 | D194: Chukwudi Eze | E194: East | F194: Mouse Ergo | G194: Accessories | H194: ONLINE | I194: 12 | J194: 18000 | K194: =J194 -> 18000 | L194: =I194*K194 -> 216000 | M194: 0 | N194: =M194/100 * L194 -> 0 | O194: =L194-N194 -> 216000 | P194: Cancelled | Q194: Mouse Ergo | R194: Accessories | S194: ONLINE
A195: ORD-88964 | B195: 45606 | C195: CUST-2255 | D195: Tunde Fashola | E195: East | F195: Tablet Air | G195: Electronics | H195: Distributor | I195: 3 | J195: 180000 | K195: =J195 -> 180000 | L195: =I195*K195 -> 540000 | M195: 0 | N195: =M195/100 * L195 -> 0 | O195: =L195-N195 -> 540000 | P195: Completed | Q195: Tablet Air | R195: Electronics | S195: Distributor
A196: ORD-35995 | B196: 45616 | C196: CUST-4299 | D196: Yemi Osinbajo | E196: South | F196: SmartPhone X | G196: Electronics | H196: N/A | I196: 10 | J196: 220000 | K196: =J196 -> 220000 | L196: =I196*K196 -> 2200000 | M196: 20 | N196: =M196/100 * L196 -> 440000 | O196: =L196-N196 -> 1760000 | P196: Completed | Q196: SmartPhone X | R196: Electronics | S196: None
A197: ORD-65448 | B197: 45514 | C197: CUST-1574 | D197: Kemi Adebayo | E197: South | F197: Tablet Air | G197: Electronics | H197: In-Store | I197: 18 | J197: 180000 | K197: =J197 -> 180000 | L197: =I197*K197 -> 3240000 | M197: 0 | N197: =M197/100 * L197 -> 0 | O197: =L197-N197 -> 3240000 | P197: Completed | Q197: Tablet Air | R197: Electronics | S197: In-Store
A198: ORD-19545 | B198: 45481 | C198: CUST-1604 | D198: Ibrahim Musa | E198: South | F198: Mouse Ergo | G198: Accessories | H198: In-Store | I198: 13 | J198: 18000 | K198: =J198 -> 18000 | L198: =I198*K198 -> 234000 | M198: 5 | N198: =M198/100 * L198 -> 11700 | O198: =L198-N198 -> 222300 | P198: Pending | Q198: Mouse Ergo | R198: Accessories | S198: In-Store
... A242: ORD-85456 | B242: 45491 | C242: CUST-4061 | D242: Kemi Adebayo | E242: North | F242: Keyboard Mech | G242: Accessories | H242: Distributor | I242: 13 | J242: 28000 | K242: =J242 -> 28000 | L242: =I242*K242 -> 364000 | M242: 20 | N242: =M242/100 * L242 -> 72800 | O242: =L242-N242 -> 291200 | P242: Returned | Q242: Keyboard Mech | R242: Accessories | S242: Distributor
A243: ORD-65194 | B243: 45647 | C243: CUST-3030 | D243: Kemi Adebayo | E243: East | F243: Laptop pro | G243: Electronics | H243: N/A | I243: 9 | J243: 0 | K243: 450000 | L243: =I243*K243 -> 4050000 | M243: 0 | N243: =M243/100 * L243 -> 0 | O243: =L243-N243 -> 4050000 | P243: Cancelled | Q243: Laptop pro | R243: Electronics | S243: None
A244: ORD-14818 | B244: 45608 | C244: CUST-1681 | D244: Tunde Fashola | E244: North | F244: Monitor 4K | G244: Electronics | H244: Online | I244: 8 | J244: 95000 | K244: =J244 -> 95000 | L244: =I244*K244 -> 760000 | M244: 15 | N244: =M244/100 * L244 -> 114000 | O244: =L244-N244 -> 646000 | P244: Completed | Q244: Monitor 4K | R244: Electronics | S244: Online
A245: ORD-56952 | B245: 45423 | C245: CUST-4392 | D245: Tunde Fashola | E245: West | F245: SmartPhone X | G245: Electronics | H245: In-Store | I245: 7 | J245: 220000 | K245: =J245 -> 220000 | L245: =I245*K245 -> 1540000 | M245: 5 | N245: =M245/100 * L245 -> 77000 | O245: =L245-N245 -> 1463000 | P245: Completed | Q245: SmartPhone X | R245: Electronics | S245: In-Store
A246: ORD-52247 | B246: 45316 | C246: CUST-4097 | D246: James Okafor | E246: North | F246: Laptop Pro | G246: Electronics | H246: In-Store | I246: 9 | J246: 450000 | K246: =J246 -> 450000 | L246: =I246*K246 -> 4050000 | M246: 10 | N246: =M246/100 * L246 -> 405000 | O246: =L246-N246 -> 3645000 | P246: Completed | Q246: Laptop Pro | R246: Electronics | S246: In-Store
A247: ORD-28634 | B247: 45559 | C247: CUST-2139 | D247: Ibrahim Musa | E247: West | F247: Laptop Pro | G247: Electronics | H247: Online | I247: 3 | J247: 450000 | K247: =J247 -> 450000 | L247: =I247*K247 -> 1350000 | M247: 0 | N247: =M247/100 * L247 -> 0 | O247: =L247-N247 -> 1350000 | P247: Completed | Q247: Laptop Pro | R247: Electronics | S247: Online
A248: ORD-51114 | B248: 45414 | C248: CUST-3903 | D248: Yemi Osinbajo | E248: North | F248: Keyboard Mech | G248: Accessories | H248: Online | I248: 19 | J248: 28000 | K248: =J248 -> 28000 | L248: =I248*K248 -> 532000 | M248: 0 | N248: =M248/100 * L248 -> 0 | O248: =L248-N248 -> 532000 | P248: Completed | Q248: Keyboard Mech | R248: Accessories | S248: Online
A249: ORD-93719 | B249: 45328 | C249: CUST-1575 | D249: Ibrahim Musa | E249: North | F249: Keyboard Mech | G249: Accessories | H249: Distributor | I249: 13 | J249: 28000 | K249: =J249 -> 28000 | L249: =I249*K249 -> 364000 | M249: 15 | N249: =M249/100 * L249 -> 54600 | O249: =L249-N249 -> 309400 | P249: Completed | Q249: Keyboard Mech | R249: Accessories | S249: Distributor
A250: ORD-87831 | B250: 45470 | C250: CUST-3540 | D250: Kemi Adebayo | E250: North | F250: Wireless Earbuds | G250: Accessories | H250: In-Store | I250: 1 | J250: 35000 | K250: =J250 -> 35000 | L250: =I250*K250 -> 35000 | M250: 5 | N250: =M250/100 * L250 -> 1750 | O250: =L250-N250 -> 33250 | P250: Returned | Q250: Wireless Earbuds | R250: Accessories | S250: In-Store
A251: ORD-92074 | B251: 45480 | C251: CUST-3820 | D251: James Okafor | E251: North | F251: Mouse Ergo | G251: Accessories | H251: In-Store | I251: 15 | J251: 18000 | K251: =J251 -> 18000 | L251: =I251*K251 -> 270000 | M251: 0 | N251: =M251/100 * L251 -> 0 | O251: =L251-N251 -> 270000 | P251: Completed | Q251: Mouse Ergo | R251: Accessories | S251: In-Store
A252: ORD-67898 | B252: 45419 | C252: CUST-2575 | D252: Yemi Osinbajo | E252: East | F252: Monitor 4K | G252: Electronics | H252: Online | I252: 15 | J252: 95000 | K252: =J252 -> 95000 | L252: =I252*K252 -> 1425000 | M252: 20 | N252: =M252/100 * L252 -> 285000 | O252: =L252-N252 -> 1140000 | P252: Returned | Q252: Monitor 4K | R252: Electronics | S252: Online
A253: ORD-48119 | B253: 45362 | C253: CUST-4692 | D253: Tunde Fashola | E253: North | F253: Mouse Ergo | G253: Accessories | H253: In-Store | I253: 14 | J253: 18000 | K253: =J253 -> 18000 | L253: =I253*K253 -> 252000 | M253: 15 | N253: =M253/100 * L253 -> 37800 | O253: =L253-N253 -> 214200 | P253: Cancelled | Q253: Mouse Ergo | R253: Accessories | S253: In-Store
A254: ORD-53506 | B254: 45517 | C254: CUST-2388 | D254: Amaka Bello | E254: East | F254: Laptop Pro | G254: Electronics | H254: Distributor | I254: 13 | J254: 450000 | K254: =J254 -> 450000 | L254: =I254*K254 -> 5850000 | M254: 15 | N254: =M254/100 * L254 -> 877500 | O254: =L254-N254 -> 4972500 | P254: Completed | Q254: Laptop Pro | R254: Electronics | S254: Distributor
A255: ORD-54608 | B255: 45330 | C255: CUST-3949 | D255: Yemi Osinbajo | E255: South | F255: Laptop Pro | G255: Electronics | H255: Distributor | I255: 17 | J255: 450000 | K255: =J255 -> 450000 | L255: =I255*K255 -> 7650000 | M255: 0 | N255: =M255/100 * L255 -> 0 | O255: =L255-N255 -> 7650000 | P255: Completed | Q255: Laptop Pro | R255: Electronics | S255: Distributor
... A327: ORD-41056 | B327: 45377 | C327: CUST-1846 | D327: Yemi Osinbajo | E327: South | F327: Wireless Earbuds | G327: Accessories | H327: Distributor | I327: 6 | J327: 35000 | K327: =J327 -> 35000 | L327: =I327*K327 -> 210000 | M327: 10 | N327: =M327/100 * L327 -> 21000 | O327: =L327-N327 -> 189000 | P327: Completed | Q327: Wireless Earbuds | R327: Accessories | S327: Distributor
A328: ORD-43289 | B328: 45541 | C328: CUST-1302 | D328: Emeka Nwosu | E328: South | F328: Mouse Ergo | G328: Accessories | H328: Online | I328: 10 | J328: 999999999 | K328: 18000 | L328: =I328*K328 -> 180000 | M328: 15 | N328: =M328/100 * L328 -> 27000 | O328: =L328-N328 -> 153000 | P328: Completed | Q328: Mouse Ergo | R328: Accessories | S328: Online
A329: ORD-32962 | B329: 45494 | C329: CUST-4335 | D329: Tunde Fashola | E329: South | F329: Mouse Ergo | G329: Accessories | H329: Online | I329: 6 | J329: 18000 | K329: =J329 -> 18000 | L329: =I329*K329 -> 108000 | M329: 10 | N329: =M329/100 * L329 -> 10800 | O329: =L329-N329 -> 97200 | P329: Returned | Q329: Mouse Ergo | R329: Accessories | S329: Online
...

Sheet Clean Calc Table
A1: Order ID | B1: Product | C1: Quantity | D1: Unit Price (₦) | E1: Discount (%) | F1: Status | G1: Revenue (₦) | H1: Discounted Revenue (₦) | I1: VAT 7.5% (₦) | J1: Net Revenue (₦) | K1: Category (XLOOKUP) | L1: Supplier Name | M1: Warranty (INDEX-MATCH) | N1: SKU
A2: ORD-47512 | B2: Wireless Earbuds | C2: 7 | D2: 35000 | E2: 10 | F2: Pending | G2: =C2*D2 -> 245000 | H2: =G2*(1-E2/100) -> 220500 | I2: =H2*0.075 -> 16537.5 | J2: =H2+I2 -> 237037.5 | K2: =IFERROR(_xlfn.XLOOKUP(B:B,LOOKUP_TABLES!A:A,LOOKUP_TABLES!B:B),"Not Found") -> Accessories | L2: =IFERROR(_xlfn.XLOOKUP(M:M,LOOKUP_TABLES!E:E,LOOKUP_TABLES!D:D),"Not Found") -> SoundWave Co | M2: =IFERROR(INDEX(LOOKUP_TABLES!E:E,MATCH(B2,LOOKUP_TABLES!A:A,0)),"Not Found") -> 6 | N2: =_xlfn.XLOOKUP(B:B,LOOKUP_TABLES!A:A,LOOKUP_TABLES!F:F) -> SKU-1003
A3: ORD-67431 | B3: Mouse Ergo | C3: 4 | D3: 18000 | E3: 0 | F3: Completed | G3: =C3*D3 -> 72000 | H3: =G3*(1-E3/100) -> 72000 | I3: =H3*0.075 -> 5400 | J3: =H3+I3 -> 77400 | K3: =IFERROR(_xlfn.XLOOKUP(B:B,LOOKUP_TABLES!A:A,LOOKUP_TABLES!B:B),"Not Found") -> Accessories | L3: =IFERROR(_xlfn.XLOOKUP(M:M,LOOKUP_TABLES!E:E,LOOKUP_TABLES!D:D),"Not Found") -> MobileMaster NG | M3: =IFERROR(INDEX(LOOKUP_TABLES!E:E,MATCH(B3,LOOKUP_TABLES!A:A,0)),"Not Found") -> 12 | N3: =_xlfn.XLOOKUP(B:B,LOOKUP_TABLES!A:A,LOOKUP_TABLES!F:F) -> SKU-1006
A4: ORD-89777 | B4: Keyboard Mech | C4: 2 | D4: 28000 | E4: 15 | F4: Pending | G4: =C4*D4 -> 56000 | H4: =G4*(1-E4/100) -> 47600 | I4: =H4*0.075 -> 3570 | J4: =H4+I4 -> 51170 | K4: =IFERROR(_xlfn.XLOOKUP(B:B,LOOKUP_TABLES!A:A,LOOKUP_TABLES!B:B),"Not Found") -> Accessories | L4: =IFERROR(_xlfn.XLOOKUP(M:M,LOOKUP_TABLES!E:E,LOOKUP_TABLES!D:D),"Not Found") -> MobileMaster NG | M4: =IFERROR(INDEX(LOOKUP_TABLES!E:E,MATCH(B4,LOOKUP_TABLES!A:A,0)),"Not Found") -> 12 | N4: =_xlfn.XLOOKUP(B:B,LOOKUP_TABLES!A:A,LOOKUP_TABLES!F:F) -> SKU-1005
A5: ORD-84141 | B5: Webcam HD | C5: 1 | D5: 22000 | E5: 0 | F5: Completed | G5: =C5*D5 -> 22000 | H5: =G5*(1-E5/100) -> 22000 | I5: =H5*0.075 -> 1650 | J5: =H5+I5 -> 23650 | K5: =IFERROR(_xlfn.XLOOKUP(B:B,LOOKUP_TABLES!A:A,LOOKUP_TABLES!B:B),"Not Found") -> Accessories | L5: =IFERROR(_xlfn.XLOOKUP(M:M,LOOKUP_TABLES!E:E,LOOKUP_TABLES!D:D),"Not Found") -> MobileMaster NG | M5: =IFERROR(INDEX(LOOKUP_TABLES!E:E,MATCH(B5,LOOKUP_TABLES!A:A,0)),"Not Found") -> 12 | N5: =_xlfn.XLOOKUP(B:B,LOOKUP_TABLES!A:A,LOOKUP_TABLES!F:F) -> SKU-1007
A6: ORD-72684 | B6: Keyboard Mech | C6: 6 | D6: 28000 | E6: 0 | F6: Completed | G6: =C6*D6 -> 168000 | H6: =G6*(1-E6/100) -> 168000 | I6: =H6*0.075 -> 12600 | J6: =H6+I6 -> 180600 | K6: =IFERROR(_xlfn.XLOOKUP(B:B,LOOKUP_TABLES!A:A,LOOKUP_TABLES!B:B),"Not Found") -> Accessories | L6: =IFERROR(_xlfn.XLOOKUP(M:M,LOOKUP_TABLES!E:E,LOOKUP_TABLES!D:D),"Not Found") -> MobileMaster NG | M6: =IFERROR(INDEX(LOOKUP_TABLES!E:E,MATCH(B6,LOOKUP_TABLES!A:A,0)),"Not Found") -> 12 | N6: =_xlfn.XLOOKUP(B:B,LOOKUP_TABLES!A:A,LOOKUP_TABLES!F:F) -> SKU-1005
A7: ORD-88636 | B7: Mouse Ergo | C7: 4 | D7: 18000 | E7: 20 | F7: Completed | G7: =C7*D7 -> 72000 | H7: =G7*(1-E7/100) -> 57600 | I7: =H7*0.075 -> 4320 | J7: =H7+I7 -> 61920 | K7: =IFERROR(_xlfn.XLOOKUP(B:B,LOOKUP_TABLES!A:A,LOOKUP_TABLES!B:B),"Not Found") -> Accessories | L7: =IFERROR(_xlfn.XLOOKUP(M:M,LOOKUP_TABLES!E:E,LOOKUP_TABLES!D:D),"Not Found") -> MobileMaster NG | M7: =IFERROR(INDEX(LOOKUP_TABLES!E:E,MATCH(B7,LOOKUP_TABLES!A:A,0)),"Not Found") -> 12 | N7: =_xlfn.XLOOKUP(B:B,LOOKUP_TABLES!A:A,LOOKUP_TABLES!F:F) -> SKU-1006
A8: ORD-98754 | B8: Tablet Air | C8: 11 | D8: 180000 | E8: 10 | F8: Completed | G8: =C8*D8 -> 1980000 | H8: =G8*(1-E8/100) -> 1782000 | I8: =H8*0.075 -> 133650 | J8: =H8+I8 -> 1915650 | K8: =IFERROR(_xlfn.XLOOKUP(B:B,LOOKUP_TABLES!A:A,LOOKUP_TABLES!B:B),"Not Found") -> Electronics | L8: =IFERROR(_xlfn.XLOOKUP(M:M,LOOKUP_TABLES!E:E,LOOKUP_TABLES!D:D),"Not Found") -> MobileMaster NG | M8: =IFERROR(INDEX(LOOKUP_TABLES!E:E,MATCH(B8,LOOKUP_TABLES!A:A,0)),"Not Found") -> 12 | N8: =_xlfn.XLOOKUP(B:B,LOOKUP_TABLES!A:A,LOOKUP_TABLES!F:F) -> SKU-1002
A9: ORD-27224 | B9: SmartPhone X | C9: 7 | D9: 220000 | E9: 0 | F9: Completed | G9: =C9*D9 -> 1540000 | H9: =G9*(1-E9/100) -> 1540000 | I9: =H9*0.075 -> 115500 | J9: =H9+I9 -> 1655500 | K9: =IFERROR(_xlfn.XLOOKUP(B:B,LOOKUP_TABLES!A:A,LOOKUP_TABLES!B:B),"Not Found") -> Electronics | L9: =IFERROR(_xlfn.XLOOKUP(M:M,LOOKUP_TABLES!E:E,LOOKUP_TABLES!D:D),"Not Found") -> MobileMaster NG | M9: =IFERROR(INDEX(LOOKUP_TABLES!E:E,MATCH(B9,LOOKUP_TABLES!A:A,0)),"Not Found") -> 12 | N9: =_xlfn.XLOOKUP(B:B,LOOKUP_TABLES!A:A,LOOKUP_TABLES!F:F) -> SKU-1001
A10: ORD-64948 | B10: Webcam HD | C10: 8 | D10: 22000 | E10: 0 | F10: Cancelled | G10: =C10*D10 -> 176000 | H10: =G10*(1-E10/100) -> 176000 | I10: =H10*0.075 -> 13200 | J10: =H10+I10 -> 189200 | K10: =IFERROR(_xlfn.XLOOKUP(B:B,LOOKUP_TABLES!A:A,LOOKUP_TABLES!B:B),"Not Found") -> Accessories | L10: =IFERROR(_xlfn.XLOOKUP(M:M,LOOKUP_TABLES!E:E,LOOKUP_TABLES!D:D),"Not Found") -> MobileMaster NG | M10: =IFERROR(INDEX(LOOKUP_TABLES!E:E,MATCH(B10,LOOKUP_TABLES!A:A,0)),"Not Found") -> 12 | N10: =_xlfn.XLOOKUP(B:B,LOOKUP_TABLES!A:A,LOOKUP_TABLES!F:F) -> SKU-1007
A11: ORD-68459 | B11: Tablet Air | C11: 10 | D11: 180000 | E11: 5 | F11: Pending | G11: =C11*D11 -> 1800000 | H11: =G11*(1-E11/100) -> 1710000 | I11: =H11*0.075 -> 128250 | J11: =H11+I11 -> 1838250 | K11: =IFERROR(_xlfn.XLOOKUP(B:B,LOOKUP_TABLES!A:A,LOOKUP_TABLES!B:B),"Not Found") -> Electronics | L11: =IFERROR(_xlfn.XLOOKUP(M:M,LOOKUP_TABLES!E:E,LOOKUP_TABLES!D:D),"Not Found") -> MobileMaster NG | M11: =IFERROR(INDEX(LOOKUP_TABLES!E:E,MATCH(B11,LOOKUP_TABLES!A:A,0)),"Not Found") -> 12 | N11: =_xlfn.XLOOKUP(B:B,LOOKUP_TABLES!A:A,LOOKUP_TABLES!F:F) -> SKU-1002
A12: ORD-26406 | B12: Laptop Pro | C12: 19 | D12: 450000 | E12: 10 | F12: Completed | G12: =C12*D12 -> 8550000 | H12: =G12*(1-E12/100) -> 7695000 | I12: =H12*0.075 -> 577125 | J12: =H12+I12 -> 8272125 | K12: =IFERROR(_xlfn.XLOOKUP(B:B,LOOKUP_TABLES!A:A,LOOKUP_TABLES!B:B),"Not Found") -> Electronics | L12: =IFERROR(_xlfn.XLOOKUP(M:M,LOOKUP_TABLES!E:E,LOOKUP_TABLES!D:D),"Not Found") -> TechGlobal Ltd | M12: =IFERROR(INDEX(LOOKUP_TABLES!E:E,MATCH(B12,LOOKUP_TABLES!A:A,0)),"Not Found") -> 24 | N12: =_xlfn.XLOOKUP(B:B,LOOKUP_TABLES!A:A,LOOKUP_TABLES!F:F) -> SKU-1000
A13: ORD-99016 | B13: Keyboard Mech | C13: 20 | D13: 28000 | E13: 10 | F13: Completed | G13: =C13*D13 -> 560000 | H13: =G13*(1-E13/100) -> 504000 | I13: =H13*0.075 -> 37800 | J13: =H13+I13 -> 541800 | K13: =IFERROR(_xlfn.XLOOKUP(B:B,LOOKUP_TABLES!A:A,LOOKUP_TABLES!B:B),"Not Found") -> Accessories | L13: =IFERROR(_xlfn.XLOOKUP(M:M,LOOKUP_TABLES!E:E,LOOKUP_TABLES!D:D),"Not Found") -> MobileMaster NG | M13: =IFERROR(INDEX(LOOKUP_TABLES!E:E,MATCH(B13,LOOKUP_TABLES!A:A,0)),"Not Found") -> 12 | N13: =_xlfn.XLOOKUP(B:B,LOOKUP_TABLES!A:A,LOOKUP_TABLES!F:F) -> SKU-1005
... A50: ORD-94803 | B50: Laptop Pro | C50: 14 | D50: 450000 | E50: 0 | F50: Cancelled | G50: =C50*D50 -> 6300000 | H50: =G50*(1-E50/100) -> 6300000 | I50: =H50*0.075 -> 472500 | J50: =H50+I50 -> 6772500 | K50: =IFERROR(_xlfn.XLOOKUP(B:B,LOOKUP_TABLES!A:A,LOOKUP_TABLES!B:B),"Not Found") -> Electronics | L50: =IFERROR(_xlfn.XLOOKUP(M:M,LOOKUP_TABLES!E:E,LOOKUP_TABLES!D:D),"Not Found") -> TechGlobal Ltd | M50: =IFERROR(INDEX(LOOKUP_TABLES!E:E,MATCH(B50,LOOKUP_TABLES!A:A,0)),"Not Found") -> 24 | N50: =_xlfn.XLOOKUP(B:B,LOOKUP_TABLES!A:A,LOOKUP_TABLES!F:F) -> SKU-1000
A52: TOTALS | C52: =SUM(C2:C50) -> 511 | G52: =SUM(G2:G50) -> 87166000 | H52: =SUM(H2:H50) -> 79038300 | I52: =SUM(I2:I50) -> 5927872.5 | J52: =SUM(J2:J50) -> 84966172

Sheet 📋 TASK_BRIEF
B1: 🏢 TECHBRIDGE NIGERIA LTD — EXCEL ANALYST PRACTICE WORKBOOK
B3: About TechBridge Nigeria Ltd
B4: TechBridge Nigeria Ltd is a Lagos-based technology distribution company operating across 4 regions (North, South, East, West). They sell consumer electronics and accessories via Online, In-Store, and Distributor channels. You have been hired as a Junior Data Analyst. Your manager has handed you raw sales data for FY2024 and wants a full report and dashboard by Friday.
B6: TASK 1 — Text to Columns
B7: RAW_DATA sheet → Column M ('Details') is pipe-delimited. Use Data > Text to Columns to split into 3 new columns: Product_Clean | Category_Clean | Channel_Clean.
B9: TASK 2 — Data Cleaning
B10: RAW_DATA: Fix typos in Region, Status, Channel, Product columns using Find & Replace. Remove exact duplicate rows (use Remove Duplicates). Handle blank cells with 'N/A'. Correct outlier Unit Prices (flag with conditional formatting — red fill if <1000 or >600000).
B12: TASK 3 — XLOOKUP Practice
B13: CALC_TABLE column K: Write an XLOOKUP to pull Category from LOOKUP_TABLES. The formula is already in the sheet — study it, then modify it to also pull SKU into a new column.
B15: TASK 4 — INDEX / MATCH
B16: CALC_TABLE column L: An INDEX/MATCH is already pulling Warranty months. Now write one to fetch the Supplier name from LOOKUP_TABLES into a new column.
B18: TASK 5 — IFERROR Handling
... B36: ⚠️ NOTE: The data contains intentional errors for practice — typos, duplicates, missing values, outliers, and future-dated orders. Cleaning them is part of the exercise!

Sheet LOOKUP_TABLES
A1: Product | B1: Category | C1: Standard Price (₦) | D1: Supplier | E1: Warranty (Months) | F1: SKU | H1: Sales Rep | I1: Target (₦) | J1: Region
A2: Laptop Pro | B2: Electronics | C2: 450000 | D2: TechGlobal Ltd | E2: 24 | F2: SKU-1000 | H2: James Okafor | I2: 11000000 | J2: North
A3: SmartPhone X | B3: Electronics | C3: 220000 | D3: MobileMaster NG | E3: 12 | F3: SKU-1001 | H3: Amaka Bello | I3: 14000000 | J3: South
A4: Tablet Air | B4: Electronics | C4: 180000 | D4: TechGlobal Ltd | E4: 12 | F4: SKU-1002 | H4: Chukwudi Eze | I4: 24000000 | J4: East
A5: Wireless Earbuds | B5: Accessories | C5: 35000 | D5: SoundWave Co | E5: 6 | F5: SKU-1003 | H5: Ngozi Adeyemi | I5: 20000000 | J5: West
A6: Monitor 4K | B6: Electronics | C6: 95000 | D6: VisualTech Ltd | E6: 24 | F6: SKU-1004 | H6: Emeka Nwosu | I6: 18000000 | J6: North
A7: Keyboard Mech | B7: Accessories | C7: 28000 | D7: InputPro NG | E7: 12 | F7: SKU-1005 | H7: Fatima Aliyu | I7: 25000000 | J7: South
A8: Mouse Ergo | B8: Accessories | C8: 18000 | D8: InputPro NG | E8: 12 | F8: SKU-1006 | H8: Ibrahim Musa | I8: 9000000 | J8: East
A9: Webcam HD | B9: Accessories | C9: 22000 | D9: SoundWave Co | E9: 12 | F9: SKU-1007 | H9: Kemi Adebayo | I9: 13000000 | J9: West
H10: Tunde Fashola | I10: 20000000 | J10: North
H11: Yemi Osinbajo | I11: 8000000 | J11: South

Sheet RAW_DATA
A1: Order ID | B1: Order Date | C1: Customer ID | D1: Sales Rep | E1: Region | F1: Product | G1: Category | H1: Channel | I1: Quantity | J1: Unit Price (₦) | K1: Discount (%) | L1: Status | M1: Details (Use Text-to-Columns)
A2: ORD-47512 | B2: 45434 | C2: CUST-4094 | D2: Yemi Osinbajo | E2: East | F2: Wireless Earbuds | G2: Accessories | H2: Distributor | I2: 7 | J2: 35000 | K2: 10 | L2: Pending | M2: Wireless Earbuds|Accessories|Distributor
A3: ORD-67431 | B3: 45464 | C3: CUST-1447 | D3: Fatima Aliyu | E3: North | F3: Mouse Ergo | G3: Accessories | H3: Distributor | I3: 4 | J3: 18000 | K3: 0 | L3: Completed | M3: Mouse Ergo|Accessories|Distributor
A4: ORD-89777 | B4: 45513 | C4: CUST-4674 | D4: James Okafor | E4: West | F4: Keyboard Mech | G4: Accessories | H4: Distributor | I4: 2 | J4: 28000 | K4: 15 | L4: Pending | M4: Keyboard Mech|Accessories|Distributor
A5: ORD-84141 | B5: 45573 | C5: CUST-1120 | D5: Fatima Aliyu | E5: West | F5: Webcam HD | G5: Accessories | H5: Distributor | I5: 1 | J5: 22000 | K5: 0 | L5: Completed | M5: Webcam HD|Accessories|Distributor
A6: ORD-72684 | B6: 45492 | C6: CUST-2977 | D6: Chukwudi Eze | E6: North | F6: Keyboard Mech | G6: Accessories | H6: In-Store | I6: 6 | J6: 28000 | K6: 0 | L6: Completed | M6: Keyboard Mech|Accessories|In-Store
A7: ORD-88636 | B7: 45604 | C7: CUST-1008 | D7: Fatima Aliyu | E7: South | F7: Mouse Ergo | G7: Accessories | H7: Online | I7: 4 | J7: 18000 | K7: 20 | L7: Completed | M7: Mouse Ergo|Accessories|Online
A8: ORD-98754 | B8: 45488 | C8: CUST-1949 | D8: Ngozi Adeyemi | E8: North | F8: Tablet Air | G8: Electronics | H8: In-Store | I8: 11 | J8: 180000 | K8: 10 | L8: Completed | M8: Tablet Air|Electronics|In-Store
A9: ORD-27224 | B9: 45547 | C9: CUST-3174 | D9: Emeka Nwosu | E9: East | F9: SmartPhone X | G9: Electronics | H9: Online | I9: 7 | J9: 220000 | K9: 0 | L9: Completed | M9: SmartPhone X|Electronics|Online
A10: ORD-64948 | B10: 45478 | C10: CUST-3751 | D10: Fatima Aliyu | E10: East | F10: Webcam HD | G10: Accessories | H10: In-Store | I10: 8 | J10: 22000 | K10: 0 | L10: Cancelled | M10: Webcam HD|Accessories|In-Store
A11: ORD-68459 | B11: 45491 | C11: CUST-2962 | F11: Tablet Air | G11: Electronics | H11: In-Store | I11: 10 | J11: 180000 | K11: 5 | L11: Pending | M11: Tablet Air|Electronics|In-Store
A12: ORD-26406 | B12: 45357 | C12: CUST-3698 | D12: Yemi Osinbajo | E12: North | F12: Laptop Pro | G12: Electronics | H12: Online | I12: 19 | J12: 450000 | K12: 10 | L12: Completed | M12: Laptop Pro|Electronics|Online
A13: ORD-99016 | B13: 45304 | C13: CUST-3424 | D13: Chukwudi Eze | E13: East | F13: Keyboard Mech | G13: Accessories | H13: Online | I13: 20 | J13: 28000 | K13: 10 | L13: Completed | M13: Keyboard Mech|Accessories|Online
A14: ORD-95800 | B14: 45652 | C14: CUST-2442 | D14: Emeka Nwosu | E14: East | F14: Monitor 4K | G14: Electronics | H14: Online | I14: 15 | J14: 95000 | K14: 0 | L14: Completed | M14: Monitor 4K|Electronics|Online
A15: ORD-94614 | B15: 45563 | C15: CUST-2531 | D15: Ngozi Adeyemi | E15: West | F15: SmartPhone X | G15: Electronics | H15: In-Store | I15: 16 | J15: 220000 | K15: 20 | L15: Completed | M15: SmartPhone X|Electronics|In-Store
A16: ORD-54350 | B16: 45483 | C16: CUST-2032 | D16: Fatima Aliyu | E16: North | F16: Laptop Pro | G16: Electronics | H16: Distributor | I16: 18 | J16: 450000 | K16: 15 | L16: Completed | M16: Laptop Pro|Electronics|Distributor
A17: ORD-53207 | B17: 45424 | C17: CUST-1424 | D17: Ibrahim Musa | E17: East | F17: SmartPhone X | G17: Electronics | I17: 10 | J17: 220000 | K17: 10 | L17: Completed | M17: SmartPhone X|Electronics|None
A18: ORD-49008 | B18: 45561 | C18: CUST-3955 | D18: Ngozi Adeyemi | E18: South | F18: Laptop Pro | G18: Electronics | H18: Online | I18: 16 | J18: 450000 | K18: 0 | L18: Cancelled | M18: Laptop Pro|Electronics|Online
A19: ORD-18357 | B19: 45376 | C19: CUST-1554 | D19: James Okafor | E19: North | F19: Webcam HD | G19: Accessories | H19: Online | I19: 10 | J19: 22000 | K19: 5 | L19: Completed | M19: Webcam HD|Accessories|Online
A20: ORD-25194 | B20: 45399 | C20: CUST-2481 | D20: Tunde Fashola | E20: East | F20: Keyboard Mech | G20: Accessories | H20: Online | I20: 14 | J20: 28000 | K20: 0 | L20: Completed | M20: Keyboard Mech|Accessories|Online
A21: ORD-13478 | B21: 45574 | C21: CUST-4315 | D21: Ngozi Adeyemi | E21: South | F21: Webcam HD | G21: Accessories | H21: In-Store | I21: 8 | J21: 22000 | K21: 5 | L21: Completed | M21: Webcam HD|Accessories|In-Store
A22: ORD-60940 | B22: 45631 | C22: CUST-4626 | D22: Fatima Aliyu | E22: South | F22: Mouse Ergo | G22: Accessories | H22: In-Store | I22: 19 | J22: 18000 | K22: 15 | L22: Completed | M22: Mouse Ergo|Accessories|In-Store
A23: ORD-77286 | B23: 45475 | C23: CUST-2623 | D23: Ibrahim Musa | E23: North | F23: Tablet Air | G23: Electronics | H23: In-Store | I23: 12 | J23: 180000 | K23: 0 | L23: Completed | M23: Tablet Air|Electronics|In-Store
A24: ORD-25194 | B24: 45399 | C24: CUST-2481 | D24: Tunde Fashola | E24: East | F24: Keyboard Mech | G24: Accessories | H24: Online | I24: 14 | J24: 28000 | K24: 0 | L24: Completed | M24: Keyboard Mech|Accessories|Online
A25: ORD-59131 | B25: 45357 | C25: CUST-1717 | D25: Chukwudi Eze | E25: South | F25: Keyboard Mech | G25: Accessories | H25: In-Store | I25: 19 | J25: 28000 | K25: 15 | L25: Completed | M25: Keyboard Mech|Accessories|In-Store
A26: ORD-77154 | B26: 45557 | C26: CUST-2263 | D26: Fatima Aliyu | E26: West | F26: SmartPhone X | G26: Electronics | H26: ONLINE | I26: 19 | J26: 220000 | K26: 5 | L26: Returned | M26: SmartPhone X|Electronics|ONLINE
A27: ORD-23173 | B27: 45301 | C27: CUST-2468 | D27: Chukwudi Eze | E27: South | F27: Mouse Ergo | G27: Accessories | H27: Distributor | I27: 2 | J27: 18000 | K27: 0 | L27: Completed | M27: Mouse Ergo|Accessories|Distributor
A28: ORD-87278 | B28: 45449 | C28: CUST-2238 | D28: Yemi Osinbajo | E28: East | F28: Webcam HD | G28: Accessories | H28: On-Line | I28: 10 | J28: 22000 | K28: 0 | L28: Pending | M28: Webcam HD|Accessories|On-Line
A29: ORD-96400 | B29: 45577 | C29: CUST-3999 | D29: Amaka Bello | E29: South | F29: Tablet Air | G29: Electronics | H29: Online | I29: 15 | J29: 180000 | K29: 0 | L29: Returned | M29: Tablet Air|Electronics|Online
... A46: ORD-58655 | B46: 45360 | C46: CUST-2840 | D46: Amaka Bello | E46: South | F46: Webcam HD | G46: Accessories | H46: In-Store | I46: 10 | J46: 22000 | K46: 0 | L46: Completed | M46: Webcam HD|Accessories|In-Store
A47: ORD-80075 | B47: 45416 | C47: CUST-2928 | E47: North | F47: Mouse Ergo | G47: Accessories | H47: Distributor | I47: 18 | J47: 18000 | K47: 0 | L47: Completed | M47: Mouse Ergo|Accessories|Distributor
A48: ORD-95969 | B48: 45609 | C48: CUST-3004 | D48: Chukwudi Eze | E48: South | F48: Tablet Air | G48: Electronics | H48: In-Store | I48: 8 | J48: 180000 | K48: 20 | L48: Cancelled | M48: Tablet Air|Electronics|In-Store
A49: ORD-20589 | B49: 45615 | C49: CUST-3246 | D49: Yemi Osinbajo | E49: south | F49: Monitor 4K | G49: Electronics | H49: online | I49: 9 | J49: 95000 | K49: 10 | L49: Compelted | M49: Monitor 4K|Electronics|online
A50: ORD-55143 | B50: 45479 | C50: CUST-4090 | D50: Tunde Fashola | E50: East | F50: Keyboard Mech | G50: Accessories | H50: Online | I50: 5 | J50: 28000 | K50: 0 | L50: Completed | M50: Keyboard Mech|Accessories|Online
A51: ORD-94803 | B51: 45295 | C51: CUST-2059 | D51: Yemi Osinbajo | E51: South | F51: Laptop Pro | G51: Electronics | H51: Online | I51: 14 | J51: 450000 | K51: 0 | L51: Cancelled | M51: Laptop Pro|Electronics|Online
A52: ORD-74340 | B52: 45449 | C52: CUST-4954 | D52: James Okafor | E52: North | F52: SmartPhone X | G52: Electronics | H52: Distributor | I52: 16 | J52: 220000 | K52: 5 | L52: Completed | M52: SmartPhone X|Electronics|Distributor
A53: ORD-35614 | B53: 45547 | C53: CUST-3604 | D53: Ngozi Adeyemi | E53: SOUTH | F53: Webcam HD | G53: Accessories | H53: online | I53: 1 | J53: 22000 | K53: 0 | L53: completed | M53: Webcam HD|Accessories|online
A54: ORD-91851 | B54: 45574 | C54: CUST-3667 | D54: Yemi Osinbajo | E54: North | F54: Monitor 4K | G54: Electronics | H54: Online | I54: 2 | J54: 95000 | K54: 15 | L54: Completed | M54: Monitor 4K|Electronics|Online
A55: ORD-62205 | B55: 45495 | C55: CUST-4672 | D55: Emeka Nwosu | E55: South | F55: SmartPhone X | G55: Electronics | H55: In-Store | I55: 19 | J55: 220000 | K55: 20 | L55: Pending | M55: SmartPhone X|Electronics|In-Store
A56: ORD-61374 | B56: 45622 | C56: CUST-2345 | D56: Yemi Osinbajo | E56: South | F56: Tablet Air | G56: Electronics | H56: Online | I56: 18 | J56: 180000 | K56: 5 | L56: Returned | M56: Tablet Air|Electronics|Online
A57: ORD-19869 | B57: 45474 | C57: CUST-2083 | D57: Ngozi Adeyemi | E57: East | F57: Tablet Air | G57: Electronics | H57: Online | I57: 3 | J57: 180000 | K57: 20 | L57: Cancelled | M57: Tablet Air|Electronics|Online
A58: ORD-18357 | B58: 45376 | C58: CUST-1554 | D58: James Okafor | E58: North | F58: Webcam HD | G58: Accessories | H58: Online | I58: 10 | J58: 22000 | K58: 5 | L58: Completed | M58: Webcam HD|Accessories|Online
A59: ORD-69343 | B59: 45355 | C59: CUST-1673 | D59: Ngozi Adeyemi | E59: North | F59: Laptop Pro | G59: Electronics | H59: In-Store | I59: 19 | J59: 450000 | K59: 0 | L59: Completed | M59: Laptop Pro|Electronics|In-Store
... A67: ORD-88956 | B67: 45467 | C67: CUST-1318 | D67: Yemi Osinbajo | E67: Souht | F67: Monitor 4K | G67: Electronics | H67: in-store | I67: 16 | J67: 95000 | K67: 0 | L67: COMPLETED | M67: Monitor 4K|Electronics|in-store
A68: ORD-34983 | B68: 45544 | C68: CUST-4360 | D68: Chukwudi Eze | F68: Webcam HD | G68: Accessories | H68: Online | I68: 14 | J68: 22000 | L68: Returned | M68: Webcam HD|Accessories|Online
A69: ORD-38679 | B69: 45362 | C69: CUST-3936 | D69: Tunde Fashola | E69: West | F69: Laptop Pro | G69: Electronics | H69: Online | I69: 20 | J69: 450000 | K69: 0 | L69: Cancelled | M69: Laptop Pro|Electronics|Online
A70: ORD-44116 | B70: 45379 | C70: CUST-1303 | D70: Ngozi Adeyemi | E70: North | F70: Mouse Ergo | G70: Accessories | H70: Distributor | I70: 7 | J70: 18000 | K70: 0 | L70: Completed | M70: Mouse Ergo|Accessories|Distributor
A71: ORD-32185 | B71: 45349 | C71: CUST-3737 | E71: West | F71: Tablet Air | G71: Electronics | H71: In-Store | I71: 17 | J71: 180000 | K71: 0 | L71: Completed | M71: Tablet Air|Electronics|In-Store
A72: ORD-17367 | B72: 45554 | C72: CUST-1118 | D72: Chukwudi Eze | E72: NORTH | F72: Webcam HD | G72: Accessories | H72: Distributor | I72: 5 | J72: 22000 | K72: 20 | L72: completed | M72: Webcam HD|Accessories|Distributor
A73: ORD-70161 | B73: 45308 | C73: CUST-3713 | D73: Ngozi Adeyemi | E73: West | F73: Laptop Pro | G73: Electronics | H73: Distributor | I73: 19 | J73: 450000 | K73: 0 | L73: Completed | M73: Laptop Pro|Electronics|Distributor
A74: ORD-47941 | B74: 45525 | C74: CUST-3225 | D74: James Okafor | E74: East | F74: Laptop Pro | G74: Electronics | H74: In-Store | I74: 11 | J74: 450000 | K74: 0 | L74: Completed | M74: Laptop Pro|Electronics|In-Store
A75: ORD-22183 | B75: 45439 | C75: CUST-2579 | D75: Fatima Aliyu | E75: South | F75: Monitor 4K | G75: Electronics | H75: Online | I75: 13 | J75: 95000 | K75: 5 | L75: Completed | M75: Monitor 4K|Electronics|Online
A76: ORD-69988 | B76: 45429 | C76: CUST-2631 | D76: Emeka Nwosu | E76: South | F76: Laptop Pro | G76: Electronics | H76: Online | I76: 2 | J76: 450000 | K76: 0 | L76: Pending | M76: Laptop Pro|Electronics|Online
A77: ORD-29340 | B77: 45355 | C77: CUST-3707 | D77: Emeka Nwosu | E77: East | F77: Laptop Pro | G77: Electronics | H77: In-Store | I77: 18 | J77: 450000 | K77: 0 | L77: Completed | M77: Laptop Pro|Electronics|In-Store
A78: ORD-93810 | B78: 45630 | C78: CUST-3771 | D78: James Okafor | E78: South | F78: SmartPhone X | G78: Electronics | H78: Distributor | I78: 8 | J78: 220000 | K78: 0 | L78: Pending | M78: SmartPhone X|Electronics|Distributor
A79: ORD-56438 | B79: 45637 | C79: CUST-4279 | D79: Ibrahim Musa | E79: West | F79: Keyboard Mech | G79: Accessories | H79: Online | I79: 2 | J79: 28000 | K79: 5 | L79: Completed | M79: Keyboard Mech|Accessories|Online
A80: ORD-25717 | B80: 45448 | C80: CUST-1373 | D80: Chukwudi Eze | E80: East | F80: SmartPhone X | G80: Electronics | H80: Distributor | I80: 7 | J80: 220000 | K80: 20 | L80: Completed | M80: SmartPhone X|Electronics|Distributor
A81: ORD-11238 | B81: 45339 | C81: CUST-4764 | D81: Amaka Bello | E81: West | F81: Tablet Air | G81: Electronics | H81: Online | I81: 19 | J81: 180000 | K81: 20 | L81: Cancelled | M81: Tablet Air|Electronics|Online
A82: ORD-95054 | B82: 45345 | C82: CUST-1389 | D82: James Okafor | E82: West | F82: Tablet Air | G82: Electronics | H82: Distributor | I82: 14 | J82: 180000 | K82: 15 | L82: Pending | M82: Tablet Air|Electronics|Distributor
A83: ORD-16522 | B83: 45482 | C83: CUST-1882 | D83: Emeka Nwosu | E83: West | F83: SmartPhone X | G83: Electronics | H83: Online | I83: 20 | J83: 220000 | K83: 5 | L83: Completed | M83: SmartPhone X|Electronics|Online
... A113: ORD-49467 | B113: 45631 | C113: CUST-2715 | D113: Amaka Bello | E113: South | F113: Keyboard Mech | G113: Accessories | H113: In-Store | I113: 20 | J113: 28000 | K113: 10 | L113: Returned | M113: Keyboard Mech|Accessories|In-Store
A114: ORD-63636 | B114: 45480 | C114: CUST-2872 | D114: Emeka Nwosu | E114: North | F114: SmartPhone X | G114: Electronics | I114: 4 | J114: 220000 | K114: 20 | L114: Pending | M114: SmartPhone X|Electronics|None
A115: ORD-42444 | B115: 46150 | C115: CUST-4325 | D115: James Okafor | E115: West | F115: Laptop Pro | G115: Electronics | H115: Distributor | I115: 3 | J115: 450000 | K115: 5 | L115: Cancelled | M115: Laptop Pro|Electronics|Distributor
A116: ORD-32216 | B116: 45365 | C116: CUST-2130 | D116: Emeka Nwosu | E116: East | F116: Tablet Air | G116: Electronics | H116: Distributor | I116: 5 | J116: 180000 | K116: 0 | L116: Completed | M116: Tablet Air|Electronics|Distributor
A117: ORD-82140 | B117: 45386 | C117: CUST-3954 | D117: Fatima Aliyu | E117: South | F117: Monitor 4K | G117: Electronics | H117: Online | I117: 10 | J117: 95000 | K117: 0 | L117: Returned | M117: Monitor 4K|Electronics|Online
A118: ORD-87296 | B118: 45523 | C118: CUST-4611 | D118: Tunde Fashola | E118: North | F118: Wireless Earbuds | G118: Accessories | H118: Online | I118: 18 | J118: 35000 | L118: Completed | M118: Wireless Earbuds|Accessories|Online
A119: ORD-64206 | B119: 45506 | C119: CUST-4982 | D119: Emeka Nwosu | E119: North | F119: Laptop Pro | G119: Electronics | H119: In-Store | I119: 14 | J119: 450000 | K119: 10 | L119: Completed | M119: Laptop Pro|Electronics|In-Store
A120: ORD-43491 | B120: 45364 | C120: CUST-3181 | D120: Fatima Aliyu | E120: North | F120: Laptop Pro | G120: Electronics | H120: Online | I120: 14 | J120: 450000 | K120: 0 | L120: Completed | M120: Laptop Pro|Electronics|Online
A121: ORD-52245 | B121: 45587 | C121: CUST-2552 | E121: East | F121: Wireless Earbuds | G121: Accessories | H121: Online | I121: 15 | J121: 35000 | K121: 10 | L121: Pending | M121: Wireless Earbuds|Accessories|Online
A122: ORD-85511 | B122: 45613 | C122: CUST-1905 | D122: Yemi Osinbajo | E122: North | F122: Monitor 4K | G122: Electronics | H122: Distributor | I122: 10 | J122: 95000 | K122: 0 | L122: Pending | M122: Monitor 4K|Electronics|Distributor
A123: ORD-64732 | B123: 45398 | C123: CUST-3255 | D123: Chukwudi Eze | E123: South | F123: Laptop Pro | G123: Electronics | H123: Distributor | I123: 13 | J123: 450000 | K123: 10 | L123: Pending | M123: Laptop Pro|Electronics|Distributor
A124: ORD-41278 | B124: 45567 | C124: CUST-2266 | D124: Ngozi Adeyemi | E124: North | F124: Laptop Pro | G124: Electronics | H124: Online | I124: 15 | J124: -5000 | K124: 10 | L124: Completed | M124: Laptop Pro|Electronics|Online
A125: ORD-25572 | B125: 45358 | C125: CUST-3467 | D125: Amaka Bello | E125: West | F125: Tablet Air | G125: Electronics | H125: Distributor | I125: 18 | J125: 180000 | K125: 0 | L125: Cancelled | M125: Tablet Air|Electronics|Distributor
A126: ORD-46002 | B126: 45293 | C126: CUST-2510 | D126: Fatima Aliyu | E126: North | F126: Laptop Pro | G126: Electronics | H126: Online | I126: 15 | J126: 450000 | K126: 5 | L126: Returned | M126: Laptop Pro|Electronics|Online
A127: ORD-96752 | B127: 45644 | C127: CUST-1249 | D127: Chukwudi Eze | E127: South | F127: Mouse Ergo | G127: Accessories | H127: Distributor | I127: 2 | J127: 18000 | K127: 10 | L127: Pending | M127: Mouse Ergo|Accessories|Distributor
A128: ORD-46512 | B128: 45635 | C128: CUST-1118 | D128: Ibrahim Musa | E128: East | F128: Wireless Earbuds | G128: Accessories | H128: In-Store | I128: 20 | J128: 35000 | K128: 15 | L128: Completed | M128: Wireless Earbuds|Accessories|In-Store
A129: ORD-35415 | B129: 45419 | C129: CUST-1710 | D129: Fatima Aliyu | E129: South | F129: Monitor 4K | G129: Electronics | H129: In-Store | I129: 4 | J129: 95000 | K129: 0 | L129: Pending | M129: Monitor 4K|Electronics|In-Store
A130: ORD-43980 | B130: 45482 | C130: CUST-3145 | D130: Fatima Aliyu | E130: South | F130: Tablet Air | G130: Electronics | H130: Distributor | I130: 1 | J130: 180000 | K130: 0 | L130: Completed | M130: Tablet Air|Electronics|Distributor
A131: ORD-86344 | B131: 45337 | C131: CUST-2256 | D131: Emeka Nwosu | E131: South | F131: Laptop Pro | G131: Electronics | H131: Distributor | I131: 2 | J131: 450000 | K131: 15 | L131: Pending | M131: Laptop Pro|Electronics|Distributor
A132: ORD-62550 | B132: 45550 | C132: CUST-1032 | D132: Kemi Adebayo | E132: East | F132: SmartPhone X | G132: Electronics | H132: Distributor | I132: 11 | J132: 220000 | K132: 0 | L132: Returned | M132: SmartPhone X|Electronics|Distributor
A133: ORD-67014 | B133: 45637 | C133: CUST-2302 | D133: Ngozi Adeyemi | E133: East | F133: Tablet Air | G133: Electronics | H133: Distributor | I133: 13 | J133: 180000 | K133: 15 | L133: Cancelled | M133: Tablet Air|Electronics|Distributor
... A154: ORD-11620 | B154: 45558 | C154: CUST-3869 | D154: Yemi Osinbajo | E154: South | F154: Webcam HD | G154: Accessories | H154: In-Store | I154: 11 | J154: 22000 | K154: 10 | L154: Pending | M154: Webcam HD|Accessories|In-Store
A155: ORD-99070 | B155: 45476 | C155: CUST-1475 | D155: Chukwudi Eze | E155: East | F155: Webcam HD | G155: Accessories | I155: 4 | J155: 22000 | K155: 0 | L155: Completed | M155: Webcam HD|Accessories|None
A156: ORD-80329 | B156: 45604 | C156: CUST-2931 | D156: Kemi Adebayo | E156: East | F156: SmartPhone X | G156: Electronics | H156: Distributor | I156: 12 | J156: 220000 | K156: 0 | L156: Completed | M156: SmartPhone X|Electronics|Distributor
A157: ORD-89807 | B157: 45299 | C157: CUST-2719 | D157: Ibrahim Musa | E157: North | F157: Webcam HD | G157: Accessories | H157: Distributor | I157: 10 | J157: 22000 | K157: 0 | L157: Pending | M157: Webcam HD|Accessories|Distributor
A158: ORD-51104 | B158: 45350 | C158: CUST-1761 | D158: James Okafor | E158: North | F158: Laptop Pro | G158: Electronics | H158: Online | I158: 2 | J158: 450000 | K158: 10 | L158: Completed | M158: Laptop Pro|Electronics|Online
A159: ORD-16734 | B159: 45586 | C159: CUST-3811 | D159: Kemi Adebayo | E159: North | F159: Laptop Pro | G159: Electronics | H159: Online | I159: 16 | J159: 450000 | K159: 0 | L159: Completed | M159: Laptop Pro|Electronics|Online
A160: ORD-14852 | B160: 45550 | C160: CUST-1062 | D160: Tunde Fashola | E160: North | F160: Tablet Air | G160: Electronics | H160: Distributor | I160: 15 | J160: 180000 | K160: 0 | L160: Completed | M160: Tablet Air|Electronics|Distributor
A161: ORD-25328 | B161: 45370 | C161: CUST-2571 | D161: Fatima Aliyu | E161: South | F161: Tablet Air | G161: Electronics | H161: In-Store | I161: 14 | J161: 180000 | K161: 10 | L161: Completed | M161: Tablet Air|Electronics|In-Store
A162: ORD-18981 | B162: 45311 | C162: CUST-1335 | D162: Ngozi Adeyemi | E162: West | F162: SmartPhone X | G162: Electronics | H162: Online | I162: 19 | J162: 220000 | K162: 10 | L162: Pending | M162: SmartPhone X|Electronics|Online
A163: ORD-71487 | B163: 45369 | C163: CUST-4851 | D163: Yemi Osinbajo | E163: North | F163: Mouse Ergo | G163: Accessories | H163: Online | I163: 9 | J163: 18000 | K163: 0 | L163: Completed | M163: Mouse Ergo|Accessories|Online
A164: ORD-46877 | B164: 45336 | C164: CUST-1548 | D164: Yemi Osinbajo | E164: East | F164: Mouse Ergo | G164: Accessories | H164: ONLINE | I164: 18 | J164: 18000 | K164: 0 | L164: Returned | M164: Mouse Ergo|Accessories|ONLINE
A165: ORD-72580 | B165: 45423 | C165: CUST-2236 | D165: Ngozi Adeyemi | E165: North | F165: Monitor 4K | G165: Electronics | H165: Distributor | I165: 8 | J165: 95000 | K165: 5 | L165: Completed | M165: Monitor 4K|Electronics|Distributor
A166: ORD-67154 | B166: 45344 | C166: CUST-4771 | D166: Tunde Fashola | E166: East | F166: Laptop Pro | G166: Electronics | H166: In-Store | I166: 12 | J166: -5000 | K166: 5 | L166: Pending | M166: Laptop Pro|Electronics|In-Store
A167: ORD-33496 | B167: 45544 | C167: CUST-4339 | D167: Amaka Bello | E167: North | F167: SmartPhone X | G167: Electronics | H167: In-Store | I167: 7 | J167: 220000 | K167: 10 | L167: Pending | M167: SmartPhone X|Electronics|In-Store
... A171: ORD-64090 | B171: 45393 | C171: CUST-3648 | D171: Tunde Fashola | E171: North | F171: Keyboard Mech | G171: Accessories | H171: In-Store | I171: 8 | J171: 28000 | K171: 0 | L171: Completed | M171: Keyboard Mech|Accessories|In-Store
A172: ORD-71918 | B172: 45520 | C172: CUST-3664 | D172: Chukwudi Eze | F172: SmartPhone X | G172: Electronics | H172: In-Store | I172: 14 | J172: 220000 | K172: 15 | L172: Completed | M172: SmartPhone X|Electronics|In-Store
A173: ORD-92614 | B173: 45403 | C173: CUST-2816 | D173: Yemi Osinbajo | E173: Nroth | F173: SmartPhone X | G173: Electronics | H173: Distributor | I173: 1 | J173: 220000 | K173: 0 | L173: Compelted | M173: SmartPhone X|Electronics|Distributor
A174: ORD-20237 | B174: 45357 | C174: CUST-2343 | D174: James Okafor | E174: East | F174: SmartPhone X | G174: Electronics | H174: In-Store | I174: 19 | J174: 220000 | K174: 10 | L174: Pending | M174: SmartPhone X|Electronics|In-Store
A175: ORD-87662 | B175: 45370 | C175: CUST-4884 | D175: Fatima Aliyu | E175: North | F175: Monitor 4K | G175: Electronics | H175: Online | I175: 19 | J175: 95000 | K175: 10 | L175: Cancelled | M175: Monitor 4K|Electronics|Online
...

Sheet CALC_TABLE
A1: Order ID | B1: Product | C1: Quantity | D1: Unit Price (₦) | E1: Discount (%) | F1: Status | G1: Revenue (₦) | H1: Discounted Revenue (₦) | I1: VAT 7.5% (₦) | J1: Net Revenue (₦) | K1: Category (XLOOKUP) | L1: Warranty (INDEX-MATCH)
A2: ORD-47512 | B2: Wireless Earbuds | C2: 7 | D2: 35000 | E2: 10 | F2: Pending | G2: =C2*D2 -> 245000 | H2: =G2*(1-E2/100) -> 220500 | I2: =H2*0.075 -> 16537.5 | J2: =H2+I2 -> 237037.5 | K2: =IFERROR(_xludf.xlookup(B2,LOOKUP_TABLES!A:A,LOOKUP_TABLES!B:B,"Not Found"),"Error") -> Error | L2: =IFERROR(INDEX(LOOKUP_TABLES!E:E,MATCH(B2,LOOKUP_TABLES!A:A,0)),"Not Found") -> 6
A3: ORD-67431 | B3: Mouse Ergo | C3: 4 | D3: 18000 | E3: 0 | F3: Completed | G3: =C3*D3 -> 72000 | H3: =G3*(1-E3/100) -> 72000 | I3: =H3*0.075 -> 5400 | J3: =H3+I3 -> 77400 | K3: =IFERROR(_xludf.xlookup(B3,LOOKUP_TABLES!A:A,LOOKUP_TABLES!B:B,"Not Found"),"Error") -> Error | L3: =IFERROR(INDEX(LOOKUP_TABLES!E:E,MATCH(B3,LOOKUP_TABLES!A:A,0)),"Not Found") -> 12
A4: ORD-89777 | B4: Keyboard Mech | C4: 2 | D4: 28000 | E4: 15 | F4: Pending | G4: =C4*D4 -> 56000 | H4: =G4*(1-E4/100) -> 47600 | I4: =H4*0.075 -> 3570 | J4: =H4+I4 -> 51170 | K4: =IFERROR(_xludf.xlookup(B4,LOOKUP_TABLES!A:A,LOOKUP_TABLES!B:B,"Not Found"),"Error") -> Error | L4: =IFERROR(INDEX(LOOKUP_TABLES!E:E,MATCH(B4,LOOKUP_TABLES!A:A,0)),"Not Found") -> 12
A5: ORD-84141 | B5: Webcam HD | C5: 1 | D5: 22000 | E5: 0 | F5: Completed | G5: =C5*D5 -> 22000 | H5: =G5*(1-E5/100) -> 22000 | I5: =H5*0.075 -> 1650 | J5: =H5+I5 -> 23650 | K5: =IFERROR(_xludf.xlookup(B5,LOOKUP_TABLES!A:A,LOOKUP_TABLES!B:B,"Not Found"),"Error") -> Error | L5: =IFERROR(INDEX(LOOKUP_TABLES!E:E,MATCH(B5,LOOKUP_TABLES!A:A,0)),"Not Found") -> 12
A6: ORD-72684 | B6: Keyboard Mech | C6: 6 | D6: 28000 | E6: 0 | F6: Completed | G6: =C6*D6 -> 168000 | H6: =G6*(1-E6/100) -> 168000 | I6: =H6*0.075 -> 12600 | J6: =H6+I6 -> 180600 | K6: =IFERROR(_xludf.xlookup(B6,LOOKUP_TABLES!A:A,LOOKUP_TABLES!B:B,"Not Found"),"Error") -> Error | L6: =IFERROR(INDEX(LOOKUP_TABLES!E:E,MATCH(B6,LOOKUP_TABLES!A:A,0)),"Not Found") -> 12
A7: ORD-88636 | B7: Mouse Ergo | C7: 4 | D7: 18000 | E7: 20 | F7: Completed | G7: =C7*D7 -> 72000 | H7: =G7*(1-E7/100) -> 57600 | I7: =H7*0.075 -> 4320 | J7: =H7+I7 -> 61920 | K7: =IFERROR(_xludf.xlookup(B7,LOOKUP_TABLES!A:A,LOOKUP_TABLES!B:B,"Not Found"),"Error") -> Error | L7: =IFERROR(INDEX(LOOKUP_TABLES!E:E,MATCH(B7,LOOKUP_TABLES!A:A,0)),"Not Found") -> 12
A8: ORD-98754 | B8: Tablet Air | C8: 11 | D8: 180000 | E8: 10 | F8: Completed | G8: =C8*D8 -> 1980000 | H8: =G8*(1-E8/100) -> 1782000 | I8: =H8*0.075 -> 133650 | J8: =H8+I8 -> 1915650 | K8: =IFERROR(_xludf.xlookup(B8,LOOKUP_TABLES!A:A,LOOKUP_TABLES!B:B,"Not Found"),"Error") -> Error | L8: =IFERROR(INDEX(LOOKUP_TABLES!E:E,MATCH(B8,LOOKUP_TABLES!A:A,0)),"Not Found") -> 12
A9: ORD-27224 | B9: SmartPhone X | C9: 7 | D9: 220000 | E9: 0 | F9: Completed | G9: =C9*D9 -> 1540000 | H9: =G9*(1-E9/100) -> 1540000 | I9: =H9*0.075 -> 115500 | J9: =H9+I9 -> 1655500 | K9: =IFERROR(_xludf.xlookup(B9,LOOKUP_TABLES!A:A,LOOKUP_TABLES!B:B,"Not Found"),"Error") -> Error | L9: =IFERROR(INDEX(LOOKUP_TABLES!E:E,MATCH(B9,LOOKUP_TABLES!A:A,0)),"Not Found") -> 12
A10: ORD-64948 | B10: Webcam HD | C10: 8 | D10: 22000 | E10: 0 | F10: Cancelled | G10: =C10*D10 -> 176000 | H10: =G10*(1-E10/100) -> 176000 | I10: =H10*0.075 -> 13200 | J10: =H10+I10 -> 189200 | K10: =IFERROR(_xludf.xlookup(B10,LOOKUP_TABLES!A:A,LOOKUP_TABLES!B:B,"Not Found"),"Error") -> Error | L10: =IFERROR(INDEX(LOOKUP_TABLES!E:E,MATCH(B10,LOOKUP_TABLES!A:A,0)),"Not Found") -> 12
A11: ORD-68459 | B11: Tablet Air | C11: 10 | D11: 180000 | E11: 5 | F11: Pending | G11: =C11*D11 -> 1800000 | H11: =G11*(1-E11/100) -> 1710000 | I11: =H11*0.075 -> 128250 | J11: =H11+I11 -> 1838250 | K11: =IFERROR(_xludf.xlookup(B11,LOOKUP_TABLES!A:A,LOOKUP_TABLES!B:B,"Not Found"),"Error") -> Error | L11: =IFERROR(INDEX(LOOKUP_TABLES!E:E,MATCH(B11,LOOKUP_TABLES!A:A,0)),"Not Found") -> 12
A12: ORD-26406 | B12: Laptop Pro | C12: 19 | D12: 450000 | E12: 10 | F12: Completed | G12: =C12*D12 -> 8550000 | H12: =G12*(1-E12/100) -> 7695000 | I12: =H12*0.075 -> 577125 | J12: =H12+I12 -> 8272125 | K12: =IFERROR(_xludf.xlookup(B12,LOOKUP_TABLES!A:A,LOOKUP_TABLES!B:B,"Not Found"),"Error") -> Error | L12: =IFERROR(INDEX(LOOKUP_TABLES!E:E,MATCH(B12,LOOKUP_TABLES!A:A,0)),"Not Found") -> 24
A13: ORD-99016 | B13: Keyboard Mech | C13: 20 | D13: 28000 | E13: 10 | F13: Completed | G13: =C13*D13 -> 560000 | H13: =G13*(1-E13/100) -> 504000 | I13: =H13*0.075 -> 37800 | J13: =H13+I13 -> 541800 | K13: =IFERROR(_xludf.xlookup(B13,LOOKUP_TABLES!A:A,LOOKUP_TABLES!B:B,"Not Found"),"Error") -> Error | L13: =IFERROR(INDEX(LOOKUP_TABLES!E:E,MATCH(B13,LOOKUP_TABLES!A:A,0)),"Not Found") -> 12
... A51: ORD-94803 | B51: Laptop Pro | C51: 14 | D51: 450000 | E51: 0 | F51: Cancelled | G51: =C51*D51 -> 6300000 | H51: =G51*(1-E51/100) -> 6300000 | I51: =H51*0.075 -> 472500 | J51: =H51+I51 -> 6772500 | K51: =IFERROR(_xludf.xlookup(B51,LOOKUP_TABLES!A:A,LOOKUP_TABLES!B:B,"Not Found"),"Error") -> Error | L51: =IFERROR(INDEX(LOOKUP_TABLES!E:E,MATCH(B51,LOOKUP_TABLES!A:A,0)),"Not Found") -> 24
A52: TOTALS | C52: =SUM(C2:C51) -> 525 | G52: =SUM(G2:G51) -> 87558000 | H52: =SUM(H2:H51) -> 79430300 | I52: =SUM(I2:I51) -> 5957272.5 | J52: =SUM(J2:J51) -> 85387572
